Compiled from "RenderEventHandler.java"
public class fi.dy.masa.malilib.event.RenderEventHandler implements fi.dy.masa.malilib.interfaces.IRenderDispatcher {
  private static final fi.dy.masa.malilib.event.RenderEventHandler INSTANCE;

  private final java.util.List<fi.dy.masa.malilib.interfaces.IRenderer> overlayRenderers;

  private final java.util.List<fi.dy.masa.malilib.interfaces.IRenderer> tooltipLastRenderers;

  private final java.util.List<fi.dy.masa.malilib.interfaces.IRenderer> worldPostDebugRenderers;

  private final java.util.List<fi.dy.masa.malilib.interfaces.IRenderer> worldPreWeatherRenderers;

  private final java.util.List<fi.dy.masa.malilib.interfaces.IRenderer> worldLastRenderers;

  private final java.util.List<fi.dy.masa.malilib.interfaces.IRenderer> specialGuiRenderers;

  public fi.dy.masa.malilib.event.RenderEventHandler();
    Code:
       0: aload_0
       1: invokespecial #49                 // Method java/lang/Object."<init>":()V
       4: aload_0
       5: new           #51                 // class java/util/ArrayList
       8: dup
       9: invokespecial #52                 // Method java/util/ArrayList."<init>":()V
      12: putfield      #54                 // Field overlayRenderers:Ljava/util/List;
      15: aload_0
      16: new           #51                 // class java/util/ArrayList
      19: dup
      20: invokespecial #52                 // Method java/util/ArrayList."<init>":()V
      23: putfield      #56                 // Field tooltipLastRenderers:Ljava/util/List;
      26: aload_0
      27: new           #51                 // class java/util/ArrayList
      30: dup
      31: invokespecial #52                 // Method java/util/ArrayList."<init>":()V
      34: putfield      #58                 // Field worldPostDebugRenderers:Ljava/util/List;
      37: aload_0
      38: new           #51                 // class java/util/ArrayList
      41: dup
      42: invokespecial #52                 // Method java/util/ArrayList."<init>":()V
      45: putfield      #60                 // Field worldPreWeatherRenderers:Ljava/util/List;
      48: aload_0
      49: new           #51                 // class java/util/ArrayList
      52: dup
      53: invokespecial #52                 // Method java/util/ArrayList."<init>":()V
      56: putfield      #62                 // Field worldLastRenderers:Ljava/util/List;
      59: aload_0
      60: new           #51                 // class java/util/ArrayList
      63: dup
      64: invokespecial #52                 // Method java/util/ArrayList."<init>":()V
      67: putfield      #64                 // Field specialGuiRenderers:Ljava/util/List;
      70: return

  public static fi.dy.masa.malilib.interfaces.IRenderDispatcher getInstance();
    Code:
       0: getstatic     #69                 // Field INSTANCE:Lfi/dy/masa/malilib/event/RenderEventHandler;
       3: areturn

  public void registerGameOverlayRenderer(fi.dy.masa.malilib.interfaces.IRenderer);
    Code:
       0: aload_0
       1: getfield      #54                 // Field overlayRenderers:Ljava/util/List;
       4: aload_1
       5: invokeinterface #78,  2           // InterfaceMethod java/util/List.contains:(Ljava/lang/Object;)Z
      10: ifne          24
      13: aload_0
      14: getfield      #54                 // Field overlayRenderers:Ljava/util/List;
      17: aload_1
      18: invokeinterface #81,  2           // InterfaceMethod java/util/List.add:(Ljava/lang/Object;)Z
      23: pop
      24: return

  public void registerTooltipLastRenderer(fi.dy.masa.malilib.interfaces.IRenderer);
    Code:
       0: aload_0
       1: getfield      #56                 // Field tooltipLastRenderers:Ljava/util/List;
       4: aload_1
       5: invokeinterface #78,  2           // InterfaceMethod java/util/List.contains:(Ljava/lang/Object;)Z
      10: ifne          24
      13: aload_0
      14: getfield      #56                 // Field tooltipLastRenderers:Ljava/util/List;
      17: aload_1
      18: invokeinterface #81,  2           // InterfaceMethod java/util/List.add:(Ljava/lang/Object;)Z
      23: pop
      24: return

  public void registerWorldPostDebugRenderer(fi.dy.masa.malilib.interfaces.IRenderer);
    Code:
       0: aload_0
       1: getfield      #58                 // Field worldPostDebugRenderers:Ljava/util/List;
       4: aload_1
       5: invokeinterface #78,  2           // InterfaceMethod java/util/List.contains:(Ljava/lang/Object;)Z
      10: ifne          24
      13: aload_0
      14: getfield      #58                 // Field worldPostDebugRenderers:Ljava/util/List;
      17: aload_1
      18: invokeinterface #81,  2           // InterfaceMethod java/util/List.add:(Ljava/lang/Object;)Z
      23: pop
      24: return

  public void registerWorldPreWeatherRenderer(fi.dy.masa.malilib.interfaces.IRenderer);
    Code:
       0: aload_0
       1: getfield      #60                 // Field worldPreWeatherRenderers:Ljava/util/List;
       4: aload_1
       5: invokeinterface #78,  2           // InterfaceMethod java/util/List.contains:(Ljava/lang/Object;)Z
      10: ifne          24
      13: aload_0
      14: getfield      #60                 // Field worldPreWeatherRenderers:Ljava/util/List;
      17: aload_1
      18: invokeinterface #81,  2           // InterfaceMethod java/util/List.add:(Ljava/lang/Object;)Z
      23: pop
      24: return

  public void registerWorldLastRenderer(fi.dy.masa.malilib.interfaces.IRenderer);
    Code:
       0: aload_0
       1: getfield      #62                 // Field worldLastRenderers:Ljava/util/List;
       4: aload_1
       5: invokeinterface #78,  2           // InterfaceMethod java/util/List.contains:(Ljava/lang/Object;)Z
      10: ifne          24
      13: aload_0
      14: getfield      #62                 // Field worldLastRenderers:Ljava/util/List;
      17: aload_1
      18: invokeinterface #81,  2           // InterfaceMethod java/util/List.add:(Ljava/lang/Object;)Z
      23: pop
      24: return

  public void registerSpecialGuiRenderer(fi.dy.masa.malilib.interfaces.IRenderer);
    Code:
       0: aload_0
       1: getfield      #64                 // Field specialGuiRenderers:Ljava/util/List;
       4: aload_1
       5: invokeinterface #78,  2           // InterfaceMethod java/util/List.contains:(Ljava/lang/Object;)Z
      10: ifne          24
      13: aload_0
      14: getfield      #64                 // Field specialGuiRenderers:Ljava/util/List;
      17: aload_1
      18: invokeinterface #81,  2           // InterfaceMethod java/util/List.add:(Ljava/lang/Object;)Z
      23: pop
      24: return

  public void onRenderGameOverlayPost(fi.dy.masa.malilib.render.GuiContext, float);
    Code:
       0: invokestatic  #98                 // Method net/minecraft/class_10209.method_64146:()Lnet/minecraft/class_3695;
       3: astore_3
       4: aload_3
       5: ldc           #100                // String malilib_game_overlay
       7: invokeinterface #106,  2          // InterfaceMethod net/minecraft/class_3695.method_15396:(Ljava/lang/String;)V
      12: aload_0
      13: getfield      #54                 // Field overlayRenderers:Ljava/util/List;
      16: invokeinterface #110,  1          // InterfaceMethod java/util/List.isEmpty:()Z
      21: ifne          97
      24: aload_0
      25: getfield      #54                 // Field overlayRenderers:Ljava/util/List;
      28: invokeinterface #114,  1          // InterfaceMethod java/util/List.iterator:()Ljava/util/Iterator;
      33: astore        4
      35: aload         4
      37: invokeinterface #119,  1          // InterfaceMethod java/util/Iterator.hasNext:()Z
      42: ifeq          97
      45: aload         4
      47: invokeinterface #123,  1          // InterfaceMethod java/util/Iterator.next:()Ljava/lang/Object;
      52: checkcast     #125                // class fi/dy/masa/malilib/interfaces/IRenderer
      55: astore        5
      57: aload_3
      58: aload         5
      60: invokeinterface #129,  1          // InterfaceMethod fi/dy/masa/malilib/interfaces/IRenderer.getProfilerSectionSupplier:()Ljava/util/function/Supplier;
      65: invokeinterface #133,  2          // InterfaceMethod net/minecraft/class_3695.method_15400:(Ljava/util/function/Supplier;)V
      70: aload         5
      72: aload_1
      73: fload_2
      74: aload_3
      75: invokeinterface #137,  4          // InterfaceMethod fi/dy/masa/malilib/interfaces/IRenderer.onRenderGameOverlayPostAdvanced:(Lfi/dy/masa/malilib/render/GuiContext;FLnet/minecraft/class_3695;)V
      80: aload         5
      82: aload_1
      83: invokeinterface #140,  2          // InterfaceMethod fi/dy/masa/malilib/interfaces/IRenderer.onRenderGameOverlayPost:(Lfi/dy/masa/malilib/render/GuiContext;)V
      88: aload_3
      89: invokeinterface #143,  1          // InterfaceMethod net/minecraft/class_3695.method_15407:()V
      94: goto          35
      97: aload_3
      98: ldc           #145                // String malilib_game_messages
     100: invokeinterface #148,  2          // InterfaceMethod net/minecraft/class_3695.method_15405:(Ljava/lang/String;)V
     105: aload_1
     106: invokestatic  #153                // Method fi/dy/masa/malilib/util/InfoUtils.renderInGameMessages:(Lfi/dy/masa/malilib/render/GuiContext;)V
     109: aload_3
     110: invokeinterface #143,  1          // InterfaceMethod net/minecraft/class_3695.method_15407:()V
     115: return

  public void onRenderTooltipComponentInsertFirst(net.minecraft.class_1792$class_9635, net.minecraft.class_1799, java.util.function.Consumer<net.minecraft.class_2561>);
    Code:
       0: aload_0
       1: getfield      #56                 // Field tooltipLastRenderers:Ljava/util/List;
       4: invokeinterface #110,  1          // InterfaceMethod java/util/List.isEmpty:()Z
       9: ifne          58
      12: aload_0
      13: getfield      #56                 // Field tooltipLastRenderers:Ljava/util/List;
      16: invokeinterface #114,  1          // InterfaceMethod java/util/List.iterator:()Ljava/util/Iterator;
      21: astore        4
      23: aload         4
      25: invokeinterface #119,  1          // InterfaceMethod java/util/Iterator.hasNext:()Z
      30: ifeq          58
      33: aload         4
      35: invokeinterface #123,  1          // InterfaceMethod java/util/Iterator.next:()Ljava/lang/Object;
      40: checkcast     #125                // class fi/dy/masa/malilib/interfaces/IRenderer
      43: astore        5
      45: aload         5
      47: aload_1
      48: aload_2
      49: aload_3
      50: invokeinterface #165,  4          // InterfaceMethod fi/dy/masa/malilib/interfaces/IRenderer.onRenderTooltipComponentInsertFirst:(Lnet/minecraft/class_1792$class_9635;Lnet/minecraft/class_1799;Ljava/util/function/Consumer;)V
      55: goto          23
      58: return

  public void onRenderTooltipComponentInsertMiddle(net.minecraft.class_1792$class_9635, net.minecraft.class_1799, java.util.function.Consumer<net.minecraft.class_2561>);
    Code:
       0: aload_0
       1: getfield      #56                 // Field tooltipLastRenderers:Ljava/util/List;
       4: invokeinterface #110,  1          // InterfaceMethod java/util/List.isEmpty:()Z
       9: ifne          58
      12: aload_0
      13: getfield      #56                 // Field tooltipLastRenderers:Ljava/util/List;
      16: invokeinterface #114,  1          // InterfaceMethod java/util/List.iterator:()Ljava/util/Iterator;
      21: astore        4
      23: aload         4
      25: invokeinterface #119,  1          // InterfaceMethod java/util/Iterator.hasNext:()Z
      30: ifeq          58
      33: aload         4
      35: invokeinterface #123,  1          // InterfaceMethod java/util/Iterator.next:()Ljava/lang/Object;
      40: checkcast     #125                // class fi/dy/masa/malilib/interfaces/IRenderer
      43: astore        5
      45: aload         5
      47: aload_1
      48: aload_2
      49: aload_3
      50: invokeinterface #172,  4          // InterfaceMethod fi/dy/masa/malilib/interfaces/IRenderer.onRenderTooltipComponentInsertMiddle:(Lnet/minecraft/class_1792$class_9635;Lnet/minecraft/class_1799;Ljava/util/function/Consumer;)V
      55: goto          23
      58: return

  public void onRenderTooltipComponentInsertLast(net.minecraft.class_1792$class_9635, net.minecraft.class_1799, java.util.function.Consumer<net.minecraft.class_2561>);
    Code:
       0: aload_0
       1: getfield      #56                 // Field tooltipLastRenderers:Ljava/util/List;
       4: invokeinterface #110,  1          // InterfaceMethod java/util/List.isEmpty:()Z
       9: ifne          58
      12: aload_0
      13: getfield      #56                 // Field tooltipLastRenderers:Ljava/util/List;
      16: invokeinterface #114,  1          // InterfaceMethod java/util/List.iterator:()Ljava/util/Iterator;
      21: astore        4
      23: aload         4
      25: invokeinterface #119,  1          // InterfaceMethod java/util/Iterator.hasNext:()Z
      30: ifeq          58
      33: aload         4
      35: invokeinterface #123,  1          // InterfaceMethod java/util/Iterator.next:()Ljava/lang/Object;
      40: checkcast     #125                // class fi/dy/masa/malilib/interfaces/IRenderer
      43: astore        5
      45: aload         5
      47: aload_1
      48: aload_2
      49: aload_3
      50: invokeinterface #175,  4          // InterfaceMethod fi/dy/masa/malilib/interfaces/IRenderer.onRenderTooltipComponentInsertLast:(Lnet/minecraft/class_1792$class_9635;Lnet/minecraft/class_1799;Ljava/util/function/Consumer;)V
      55: goto          23
      58: return

  public void onRenderTooltipLast(fi.dy.masa.malilib.render.GuiContext, net.minecraft.class_1799, int, int);
    Code:
       0: invokestatic  #98                 // Method net/minecraft/class_10209.method_64146:()Lnet/minecraft/class_3695;
       3: astore        5
       5: aload         5
       7: ldc           #181                // String malilib_tooltip
       9: invokeinterface #106,  2          // InterfaceMethod net/minecraft/class_3695.method_15396:(Ljava/lang/String;)V
      14: aload_0
      15: getfield      #56                 // Field tooltipLastRenderers:Ljava/util/List;
      18: invokeinterface #110,  1          // InterfaceMethod java/util/List.isEmpty:()Z
      23: ifne          88
      26: aload_0
      27: getfield      #56                 // Field tooltipLastRenderers:Ljava/util/List;
      30: invokeinterface #114,  1          // InterfaceMethod java/util/List.iterator:()Ljava/util/Iterator;
      35: astore        6
      37: aload         6
      39: invokeinterface #119,  1          // InterfaceMethod java/util/Iterator.hasNext:()Z
      44: ifeq          88
      47: aload         6
      49: invokeinterface #123,  1          // InterfaceMethod java/util/Iterator.next:()Ljava/lang/Object;
      54: checkcast     #125                // class fi/dy/masa/malilib/interfaces/IRenderer
      57: astore        7
      59: aload         5
      61: aload         7
      63: invokeinterface #129,  1          // InterfaceMethod fi/dy/masa/malilib/interfaces/IRenderer.getProfilerSectionSupplier:()Ljava/util/function/Supplier;
      68: invokeinterface #184,  2          // InterfaceMethod net/minecraft/class_3695.method_15403:(Ljava/util/function/Supplier;)V
      73: aload         7
      75: aload_1
      76: aload_2
      77: iload_3
      78: iload         4
      80: invokeinterface #186,  5          // InterfaceMethod fi/dy/masa/malilib/interfaces/IRenderer.onRenderTooltipLast:(Lfi/dy/masa/malilib/render/GuiContext;Lnet/minecraft/class_1799;II)V
      85: goto          37
      88: aload         5
      90: invokeinterface #143,  1          // InterfaceMethod net/minecraft/class_3695.method_15407:()V
      95: return

  public void runRenderWorldPreWeather(org.joml.Matrix4f, org.joml.Matrix4f, net.minecraft.class_310, net.minecraft.class_9909, net.minecraft.class_9960, net.minecraft.class_4604, net.minecraft.class_4184, net.minecraft.class_4599, net.minecraft.class_3695);
    Code:
       0: aload         9
       2: ldc           #199                // String malilib_pre_weather
       4: invokeinterface #106,  2          // InterfaceMethod net/minecraft/class_3695.method_15396:(Ljava/lang/String;)V
       9: aload_0
      10: getfield      #60                 // Field worldPreWeatherRenderers:Ljava/util/List;
      13: invokeinterface #110,  1          // InterfaceMethod java/util/List.isEmpty:()Z
      18: ifne          98
      21: aload         4
      23: ldc           #199                // String malilib_pre_weather
      25: invokevirtual #205                // Method net/minecraft/class_9909.method_61911:(Ljava/lang/String;)Lnet/minecraft/class_9916;
      28: astore        10
      30: aload         5
      32: aload         10
      34: aload         5
      36: getfield      #211                // Field net/minecraft/class_9960.field_53091:Lnet/minecraft/class_9925;
      39: invokeinterface #217,  2          // InterfaceMethod net/minecraft/class_9916.method_61933:(Lnet/minecraft/class_9925;)Lnet/minecraft/class_9925;
      44: putfield      #211                // Field net/minecraft/class_9960.field_53091:Lnet/minecraft/class_9925;
      47: aload         5
      49: getfield      #211                // Field net/minecraft/class_9960.field_53091:Lnet/minecraft/class_9925;
      52: astore        11
      54: aload         10
      56: aload_0
      57: aload         11
      59: aload         9
      61: aload_1
      62: aload_2
      63: aload         6
      65: aload         7
      67: aload         8
      69: invokedynamic #234,  0            // InvokeDynamic #0:run:(Lfi/dy/masa/malilib/event/RenderEventHandler;Lnet/minecraft/class_9925;Lnet/minecraft/class_3695;Lorg/joml/Matrix4f;Lorg/joml/Matrix4f;Lnet/minecraft/class_4604;Lnet/minecraft/class_4184;Lnet/minecraft/class_4599;)Ljava/lang/Runnable;
      74: invokeinterface #238,  2          // InterfaceMethod net/minecraft/class_9916.method_61929:(Ljava/lang/Runnable;)V
      79: aload_0
      80: getfield      #60                 // Field worldPreWeatherRenderers:Ljava/util/List;
      83: invokeinterface #110,  1          // InterfaceMethod java/util/List.isEmpty:()Z
      88: ifne          98
      91: aload         10
      93: invokeinterface #241,  1          // InterfaceMethod net/minecraft/class_9916.method_61924:()V
      98: aload         9
     100: invokeinterface #143,  1          // InterfaceMethod net/minecraft/class_3695.method_15407:()V
     105: return

  public void runRenderWorldLast(org.joml.Matrix4f, org.joml.Matrix4f, net.minecraft.class_310, net.minecraft.class_9909, net.minecraft.class_9960, net.minecraft.class_4604, net.minecraft.class_4184, net.minecraft.class_4599, net.minecraft.class_3695);
    Code:
       0: aload         9
       2: ldc_w         #256                // String malilib_world_last
       5: invokeinterface #106,  2          // InterfaceMethod net/minecraft/class_3695.method_15396:(Ljava/lang/String;)V
      10: aload_0
      11: getfield      #62                 // Field worldLastRenderers:Ljava/util/List;
      14: invokeinterface #110,  1          // InterfaceMethod java/util/List.isEmpty:()Z
      19: ifne          100
      22: aload         4
      24: ldc_w         #256                // String malilib_world_last
      27: invokevirtual #205                // Method net/minecraft/class_9909.method_61911:(Ljava/lang/String;)Lnet/minecraft/class_9916;
      30: astore        10
      32: aload         5
      34: aload         10
      36: aload         5
      38: getfield      #211                // Field net/minecraft/class_9960.field_53091:Lnet/minecraft/class_9925;
      41: invokeinterface #217,  2          // InterfaceMethod net/minecraft/class_9916.method_61933:(Lnet/minecraft/class_9925;)Lnet/minecraft/class_9925;
      46: putfield      #211                // Field net/minecraft/class_9960.field_53091:Lnet/minecraft/class_9925;
      49: aload         5
      51: getfield      #211                // Field net/minecraft/class_9960.field_53091:Lnet/minecraft/class_9925;
      54: astore        11
      56: aload         10
      58: aload_0
      59: aload         9
      61: aload         11
      63: aload_1
      64: aload_2
      65: aload         6
      67: aload         7
      69: aload         8
      71: invokedynamic #264,  0            // InvokeDynamic #1:run:(Lfi/dy/masa/malilib/event/RenderEventHandler;Lnet/minecraft/class_3695;Lnet/minecraft/class_9925;Lorg/joml/Matrix4f;Lorg/joml/Matrix4f;Lnet/minecraft/class_4604;Lnet/minecraft/class_4184;Lnet/minecraft/class_4599;)Ljava/lang/Runnable;
      76: invokeinterface #238,  2          // InterfaceMethod net/minecraft/class_9916.method_61929:(Ljava/lang/Runnable;)V
      81: aload_0
      82: getfield      #62                 // Field worldLastRenderers:Ljava/util/List;
      85: invokeinterface #110,  1          // InterfaceMethod java/util/List.isEmpty:()Z
      90: ifne          100
      93: aload         10
      95: invokeinterface #241,  1          // InterfaceMethod net/minecraft/class_9916.method_61924:()V
     100: aload         9
     102: invokeinterface #143,  1          // InterfaceMethod net/minecraft/class_3695.method_15407:()V
     107: return

  public void onRegisterSpecialGuiRenderer(net.minecraft.class_11228, net.minecraft.class_4597$class_4598, net.minecraft.class_310, com.google.common.collect.ImmutableMap$Builder<java.lang.Class<? extends net.minecraft.class_11256>, net.minecraft.class_11239<?>>);
    Code:
       0: aload_0
       1: getfield      #64                 // Field specialGuiRenderers:Ljava/util/List;
       4: invokeinterface #110,  1          // InterfaceMethod java/util/List.isEmpty:()Z
       9: ifne          81
      12: aload_0
      13: getfield      #64                 // Field specialGuiRenderers:Ljava/util/List;
      16: invokeinterface #114,  1          // InterfaceMethod java/util/List.iterator:()Ljava/util/Iterator;
      21: astore        5
      23: aload         5
      25: invokeinterface #119,  1          // InterfaceMethod java/util/Iterator.hasNext:()Z
      30: ifeq          81
      33: aload         5
      35: invokeinterface #123,  1          // InterfaceMethod java/util/Iterator.next:()Ljava/lang/Object;
      40: checkcast     #125                // class fi/dy/masa/malilib/interfaces/IRenderer
      43: astore        6
      45: getstatic     #277                // Field fi/dy/masa/malilib/MaLiLib.LOGGER:Lorg/apache/logging/log4j/Logger;
      48: ldc_w         #279                // String onRegisterSpecialGuiRenderer(): render for [{}]
      51: aload         6
      53: invokeinterface #283,  1          // InterfaceMethod fi/dy/masa/malilib/interfaces/IRenderer.getClass:()Ljava/lang/Class;
      58: invokevirtual #289                // Method java/lang/Class.getName:()Ljava/lang/String;
      61: invokeinterface #295,  3          // InterfaceMethod org/apache/logging/log4j/Logger.warn:(Ljava/lang/String;Ljava/lang/Object;)V
      66: aload         6
      68: aload_1
      69: aload_2
      70: aload_3
      71: aload         4
      73: invokeinterface #297,  5          // InterfaceMethod fi/dy/masa/malilib/interfaces/IRenderer.onRegisterSpecialGuiRenderer:(Lnet/minecraft/class_11228;Lnet/minecraft/class_4597$class_4598;Lnet/minecraft/class_310;Lcom/google/common/collect/ImmutableMap$Builder;)V
      78: goto          23
      81: return

  private void lambda$runRenderWorldLast$0(net.minecraft.class_3695, net.minecraft.class_9925, org.joml.Matrix4f, org.joml.Matrix4f, net.minecraft.class_4604, net.minecraft.class_4184, net.minecraft.class_4599);
    Code:
       0: invokestatic  #307                // Method com/mojang/blaze3d/systems/RenderSystem.getShaderFog:()Lcom/mojang/blaze3d/buffers/GpuBufferSlice;
       3: astore        8
       5: aload_0
       6: getfield      #62                 // Field worldLastRenderers:Ljava/util/List;
       9: invokeinterface #114,  1          // InterfaceMethod java/util/List.iterator:()Ljava/util/Iterator;
      14: astore        9
      16: aload         9
      18: invokeinterface #119,  1          // InterfaceMethod java/util/Iterator.hasNext:()Z
      23: ifeq          96
      26: aload         9
      28: invokeinterface #123,  1          // InterfaceMethod java/util/Iterator.next:()Ljava/lang/Object;
      33: checkcast     #125                // class fi/dy/masa/malilib/interfaces/IRenderer
      36: astore        10
      38: aload_1
      39: aload         10
      41: invokeinterface #129,  1          // InterfaceMethod fi/dy/masa/malilib/interfaces/IRenderer.getProfilerSectionSupplier:()Ljava/util/function/Supplier;
      46: invokeinterface #133,  2          // InterfaceMethod net/minecraft/class_3695.method_15400:(Ljava/util/function/Supplier;)V
      51: aload         10
      53: aload_2
      54: invokeinterface #314,  1          // InterfaceMethod net/minecraft/class_9925.get:()Ljava/lang/Object;
      59: checkcast     #316                // class net/minecraft/class_276
      62: aload_3
      63: aload         4
      65: aload         5
      67: aload         6
      69: aload         7
      71: aload_1
      72: invokeinterface #320,  8          // InterfaceMethod fi/dy/masa/malilib/interfaces/IRenderer.onRenderWorldLastAdvanced:(Lnet/minecraft/class_276;Lorg/joml/Matrix4f;Lorg/joml/Matrix4f;Lnet/minecraft/class_4604;Lnet/minecraft/class_4184;Lnet/minecraft/class_4599;Lnet/minecraft/class_3695;)V
      77: aload         10
      79: aload_3
      80: aload         4
      82: invokeinterface #324,  3          // InterfaceMethod fi/dy/masa/malilib/interfaces/IRenderer.onRenderWorldLast:(Lorg/joml/Matrix4f;Lorg/joml/Matrix4f;)V
      87: aload_1
      88: invokeinterface #143,  1          // InterfaceMethod net/minecraft/class_3695.method_15407:()V
      93: goto          16
      96: aload         8
      98: invokestatic  #328                // Method com/mojang/blaze3d/systems/RenderSystem.setShaderFog:(Lcom/mojang/blaze3d/buffers/GpuBufferSlice;)V
     101: return

  private void lambda$runRenderWorldPreWeather$0(net.minecraft.class_9925, net.minecraft.class_3695, org.joml.Matrix4f, org.joml.Matrix4f, net.minecraft.class_4604, net.minecraft.class_4184, net.minecraft.class_4599);
    Code:
       0: invokestatic  #307                // Method com/mojang/blaze3d/systems/RenderSystem.getShaderFog:()Lcom/mojang/blaze3d/buffers/GpuBufferSlice;
       3: astore        8
       5: aload_1
       6: invokeinterface #314,  1          // InterfaceMethod net/minecraft/class_9925.get:()Ljava/lang/Object;
      11: checkcast     #316                // class net/minecraft/class_276
      14: astore        9
      16: aload_0
      17: getfield      #60                 // Field worldPreWeatherRenderers:Ljava/util/List;
      20: invokeinterface #114,  1          // InterfaceMethod java/util/List.iterator:()Ljava/util/Iterator;
      25: astore        10
      27: aload         10
      29: invokeinterface #119,  1          // InterfaceMethod java/util/Iterator.hasNext:()Z
      34: ifeq          90
      37: aload         10
      39: invokeinterface #123,  1          // InterfaceMethod java/util/Iterator.next:()Ljava/lang/Object;
      44: checkcast     #125                // class fi/dy/masa/malilib/interfaces/IRenderer
      47: astore        11
      49: aload_2
      50: aload         11
      52: invokeinterface #129,  1          // InterfaceMethod fi/dy/masa/malilib/interfaces/IRenderer.getProfilerSectionSupplier:()Ljava/util/function/Supplier;
      57: invokeinterface #133,  2          // InterfaceMethod net/minecraft/class_3695.method_15400:(Ljava/util/function/Supplier;)V
      62: aload         11
      64: aload         9
      66: aload_3
      67: aload         4
      69: aload         5
      71: aload         6
      73: aload         7
      75: aload_2
      76: invokeinterface #335,  8          // InterfaceMethod fi/dy/masa/malilib/interfaces/IRenderer.onRenderWorldPreWeather:(Lnet/minecraft/class_276;Lorg/joml/Matrix4f;Lorg/joml/Matrix4f;Lnet/minecraft/class_4604;Lnet/minecraft/class_4184;Lnet/minecraft/class_4599;Lnet/minecraft/class_3695;)V
      81: aload_2
      82: invokeinterface #143,  1          // InterfaceMethod net/minecraft/class_3695.method_15407:()V
      87: goto          27
      90: aload         8
      92: invokestatic  #328                // Method com/mojang/blaze3d/systems/RenderSystem.setShaderFog:(Lcom/mojang/blaze3d/buffers/GpuBufferSlice;)V
      95: return

  static {};
    Code:
       0: new           #2                  // class fi/dy/masa/malilib/event/RenderEventHandler
       3: dup
       4: invokespecial #339                // Method "<init>":()V
       7: putstatic     #69                 // Field INSTANCE:Lfi/dy/masa/malilib/event/RenderEventHandler;
      10: return
}

