Compiled from "RenderTypes.java"
public class net.minecraft.client.renderer.rendertype.RenderTypes {
  static final java.util.function.BiFunction<net.minecraft.resources.Identifier, java.lang.Boolean, net.minecraft.client.renderer.rendertype.RenderType> OUTLINE;

  public static final java.util.function.Supplier<com.mojang.blaze3d.textures.GpuSampler> MOVING_BLOCK_SAMPLER;

  private static final net.minecraft.client.renderer.rendertype.RenderType SOLID_MOVING_BLOCK;

  private static final net.minecraft.client.renderer.rendertype.RenderType CUTOUT_MOVING_BLOCK;

  private static final net.minecraft.client.renderer.rendertype.RenderType TRANSLUCENT_MOVING_BLOCK;

  private static final java.util.function.Function<net.minecraft.resources.Identifier, net.minecraft.client.renderer.rendertype.RenderType> ARMOR_CUTOUT_NO_CULL;

  private static final java.util.function.Function<net.minecraft.resources.Identifier, net.minecraft.client.renderer.rendertype.RenderType> ARMOR_TRANSLUCENT;

  private static final java.util.function.Function<net.minecraft.resources.Identifier, net.minecraft.client.renderer.rendertype.RenderType> ENTITY_SOLID;

  private static final java.util.function.Function<net.minecraft.resources.Identifier, net.minecraft.client.renderer.rendertype.RenderType> ENTITY_SOLID_Z_OFFSET_FORWARD;

  private static final java.util.function.Function<net.minecraft.resources.Identifier, net.minecraft.client.renderer.rendertype.RenderType> ENTITY_CUTOUT;

  private static final java.util.function.BiFunction<net.minecraft.resources.Identifier, java.lang.Boolean, net.minecraft.client.renderer.rendertype.RenderType> ENTITY_CUTOUT_NO_CULL;

  private static final java.util.function.BiFunction<net.minecraft.resources.Identifier, java.lang.Boolean, net.minecraft.client.renderer.rendertype.RenderType> ENTITY_CUTOUT_NO_CULL_Z_OFFSET;

  private static final java.util.function.Function<net.minecraft.resources.Identifier, net.minecraft.client.renderer.rendertype.RenderType> ITEM_ENTITY_TRANSLUCENT_CULL;

  private static final java.util.function.BiFunction<net.minecraft.resources.Identifier, java.lang.Boolean, net.minecraft.client.renderer.rendertype.RenderType> ENTITY_TRANSLUCENT;

  private static final java.util.function.BiFunction<net.minecraft.resources.Identifier, java.lang.Boolean, net.minecraft.client.renderer.rendertype.RenderType> ENTITY_TRANSLUCENT_EMISSIVE;

  private static final java.util.function.Function<net.minecraft.resources.Identifier, net.minecraft.client.renderer.rendertype.RenderType> ENTITY_SMOOTH_CUTOUT;

  private static final java.util.function.BiFunction<net.minecraft.resources.Identifier, java.lang.Boolean, net.minecraft.client.renderer.rendertype.RenderType> BEACON_BEAM;

  private static final java.util.function.Function<net.minecraft.resources.Identifier, net.minecraft.client.renderer.rendertype.RenderType> ENTITY_DECAL;

  private static final java.util.function.Function<net.minecraft.resources.Identifier, net.minecraft.client.renderer.rendertype.RenderType> ENTITY_NO_OUTLINE;

  private static final java.util.function.Function<net.minecraft.resources.Identifier, net.minecraft.client.renderer.rendertype.RenderType> ENTITY_SHADOW;

  private static final java.util.function.Function<net.minecraft.resources.Identifier, net.minecraft.client.renderer.rendertype.RenderType> DRAGON_EXPLOSION_ALPHA;

  private static final java.util.function.Function<net.minecraft.resources.Identifier, net.minecraft.client.renderer.rendertype.RenderType> EYES;

  private static final net.minecraft.client.renderer.rendertype.RenderType LEASH;

  private static final net.minecraft.client.renderer.rendertype.RenderType WATER_MASK;

  private static final net.minecraft.client.renderer.rendertype.RenderType ARMOR_ENTITY_GLINT;

  private static final net.minecraft.client.renderer.rendertype.RenderType GLINT_TRANSLUCENT;

  private static final net.minecraft.client.renderer.rendertype.RenderType GLINT;

  private static final net.minecraft.client.renderer.rendertype.RenderType ENTITY_GLINT;

  private static final java.util.function.Function<net.minecraft.resources.Identifier, net.minecraft.client.renderer.rendertype.RenderType> CRUMBLING;

  private static final java.util.function.Function<net.minecraft.resources.Identifier, net.minecraft.client.renderer.rendertype.RenderType> TEXT;

  private static final net.minecraft.client.renderer.rendertype.RenderType TEXT_BACKGROUND;

  private static final java.util.function.Function<net.minecraft.resources.Identifier, net.minecraft.client.renderer.rendertype.RenderType> TEXT_INTENSITY;

  private static final java.util.function.Function<net.minecraft.resources.Identifier, net.minecraft.client.renderer.rendertype.RenderType> TEXT_POLYGON_OFFSET;

  private static final java.util.function.Function<net.minecraft.resources.Identifier, net.minecraft.client.renderer.rendertype.RenderType> TEXT_INTENSITY_POLYGON_OFFSET;

  private static final java.util.function.Function<net.minecraft.resources.Identifier, net.minecraft.client.renderer.rendertype.RenderType> TEXT_SEE_THROUGH;

  private static final net.minecraft.client.renderer.rendertype.RenderType TEXT_BACKGROUND_SEE_THROUGH;

  private static final java.util.function.Function<net.minecraft.resources.Identifier, net.minecraft.client.renderer.rendertype.RenderType> TEXT_INTENSITY_SEE_THROUGH;

  private static final net.minecraft.client.renderer.rendertype.RenderType LIGHTNING;

  private static final net.minecraft.client.renderer.rendertype.RenderType DRAGON_RAYS;

  private static final net.minecraft.client.renderer.rendertype.RenderType DRAGON_RAYS_DEPTH;

  private static final net.minecraft.client.renderer.rendertype.RenderType TRIPWIRE_MOVING_BLOCk;

  private static final net.minecraft.client.renderer.rendertype.RenderType END_PORTAL;

  private static final net.minecraft.client.renderer.rendertype.RenderType END_GATEWAY;

  public static final net.minecraft.client.renderer.rendertype.RenderType LINES;

  public static final net.minecraft.client.renderer.rendertype.RenderType LINES_TRANSLUCENT;

  public static final net.minecraft.client.renderer.rendertype.RenderType SECONDARY_BLOCK_OUTLINE;

  private static final net.minecraft.client.renderer.rendertype.RenderType DEBUG_FILLED_BOX;

  private static final net.minecraft.client.renderer.rendertype.RenderType DEBUG_POINT;

  private static final net.minecraft.client.renderer.rendertype.RenderType DEBUG_QUADS;

  private static final net.minecraft.client.renderer.rendertype.RenderType DEBUG_TRIANGLE_FAN;

  private static final java.util.function.Function<net.minecraft.resources.Identifier, net.minecraft.client.renderer.rendertype.RenderType> WEATHER_DEPTH_WRITE;

  private static final java.util.function.Function<net.minecraft.resources.Identifier, net.minecraft.client.renderer.rendertype.RenderType> WEATHER_NO_DEPTH_WRITE;

  private static final java.util.function.Function<net.minecraft.resources.Identifier, net.minecraft.client.renderer.rendertype.RenderType> BLOCK_SCREEN_EFFECT;

  private static final java.util.function.Function<net.minecraft.resources.Identifier, net.minecraft.client.renderer.rendertype.RenderType> FIRE_SCREEN_EFFECT;

  public net.minecraft.client.renderer.rendertype.RenderTypes();
    Code:
       0: aload_0
       1: invokespecial #88                 // Method java/lang/Object."<init>":()V
       4: return

  public static net.minecraft.client.renderer.rendertype.RenderType solidMovingBlock();
    Code:
       0: getstatic     #94                 // Field SOLID_MOVING_BLOCK:Lnet/minecraft/client/renderer/rendertype/RenderType;
       3: areturn

  public static net.minecraft.client.renderer.rendertype.RenderType cutoutMovingBlock();
    Code:
       0: getstatic     #97                 // Field CUTOUT_MOVING_BLOCK:Lnet/minecraft/client/renderer/rendertype/RenderType;
       3: areturn

  public static net.minecraft.client.renderer.rendertype.RenderType translucentMovingBlock();
    Code:
       0: getstatic     #100                // Field TRANSLUCENT_MOVING_BLOCK:Lnet/minecraft/client/renderer/rendertype/RenderType;
       3: areturn

  public static net.minecraft.client.renderer.rendertype.RenderType armorCutoutNoCull(net.minecraft.resources.Identifier);
    Code:
       0: getstatic     #105                // Field ARMOR_CUTOUT_NO_CULL:Ljava/util/function/Function;
       3: aload_0
       4: invokeinterface #111,  2          // InterfaceMethod java/util/function/Function.apply:(Ljava/lang/Object;)Ljava/lang/Object;
       9: checkcast     #113                // class net/minecraft/client/renderer/rendertype/RenderType
      12: areturn

  public static net.minecraft.client.renderer.rendertype.RenderType createArmorDecalCutoutNoCull(net.minecraft.resources.Identifier);
    Code:
       0: getstatic     #121                // Field net/minecraft/client/renderer/RenderPipelines.ARMOR_DECAL_CUTOUT_NO_CULL:Lcom/mojang/blaze3d/pipeline/RenderPipeline;
       3: invokestatic  #125                // Method net/minecraft/client/renderer/rendertype/RenderSetup.builder:(Lcom/mojang/blaze3d/pipeline/RenderPipeline;)Lnet/minecraft/client/renderer/rendertype/RenderSetup$RenderSetupBuilder;
       6: ldc           #127                // String Sampler0
       8: aload_0
       9: invokevirtual #131                // Method net/minecraft/client/renderer/rendertype/RenderSetup$RenderSetupBuilder.withTexture:(Ljava/lang/String;Lnet/minecraft/resources/Identifier;)Lnet/minecraft/client/renderer/rendertype/RenderSetup$RenderSetupBuilder;
      12: invokevirtual #135                // Method net/minecraft/client/renderer/rendertype/RenderSetup$RenderSetupBuilder.useLightmap:()Lnet/minecraft/client/renderer/rendertype/RenderSetup$RenderSetupBuilder;
      15: invokevirtual #138                // Method net/minecraft/client/renderer/rendertype/RenderSetup$RenderSetupBuilder.useOverlay:()Lnet/minecraft/client/renderer/rendertype/RenderSetup$RenderSetupBuilder;
      18: getstatic     #144                // Field net/minecraft/client/renderer/rendertype/LayeringTransform.VIEW_OFFSET_Z_LAYERING:Lnet/minecraft/client/renderer/rendertype/LayeringTransform;
      21: invokevirtual #148                // Method net/minecraft/client/renderer/rendertype/RenderSetup$RenderSetupBuilder.setLayeringTransform:(Lnet/minecraft/client/renderer/rendertype/LayeringTransform;)Lnet/minecraft/client/renderer/rendertype/RenderSetup$RenderSetupBuilder;
      24: invokevirtual #151                // Method net/minecraft/client/renderer/rendertype/RenderSetup$RenderSetupBuilder.affectsCrumbling:()Lnet/minecraft/client/renderer/rendertype/RenderSetup$RenderSetupBuilder;
      27: getstatic     #155                // Field net/minecraft/client/renderer/rendertype/RenderSetup$OutlineProperty.AFFECTS_OUTLINE:Lnet/minecraft/client/renderer/rendertype/RenderSetup$OutlineProperty;
      30: invokevirtual #159                // Method net/minecraft/client/renderer/rendertype/RenderSetup$RenderSetupBuilder.setOutline:(Lnet/minecraft/client/renderer/rendertype/RenderSetup$OutlineProperty;)Lnet/minecraft/client/renderer/rendertype/RenderSetup$RenderSetupBuilder;
      33: invokevirtual #163                // Method net/minecraft/client/renderer/rendertype/RenderSetup$RenderSetupBuilder.createRenderSetup:()Lnet/minecraft/client/renderer/rendertype/RenderSetup;
      36: astore_1
      37: ldc           #165                // String armor_decal_cutout_no_cull
      39: aload_1
      40: invokestatic  #169                // Method net/minecraft/client/renderer/rendertype/RenderType.create:(Ljava/lang/String;Lnet/minecraft/client/renderer/rendertype/RenderSetup;)Lnet/minecraft/client/renderer/rendertype/RenderType;
      43: areturn

  public static net.minecraft.client.renderer.rendertype.RenderType armorTranslucent(net.minecraft.resources.Identifier);
    Code:
       0: getstatic     #174                // Field ARMOR_TRANSLUCENT:Ljava/util/function/Function;
       3: aload_0
       4: invokeinterface #111,  2          // InterfaceMethod java/util/function/Function.apply:(Ljava/lang/Object;)Ljava/lang/Object;
       9: checkcast     #113                // class net/minecraft/client/renderer/rendertype/RenderType
      12: areturn

  public static net.minecraft.client.renderer.rendertype.RenderType entitySolid(net.minecraft.resources.Identifier);
    Code:
       0: getstatic     #177                // Field ENTITY_SOLID:Ljava/util/function/Function;
       3: aload_0
       4: invokeinterface #111,  2          // InterfaceMethod java/util/function/Function.apply:(Ljava/lang/Object;)Ljava/lang/Object;
       9: checkcast     #113                // class net/minecraft/client/renderer/rendertype/RenderType
      12: areturn

  public static net.minecraft.client.renderer.rendertype.RenderType entitySolidZOffsetForward(net.minecraft.resources.Identifier);
    Code:
       0: getstatic     #180                // Field ENTITY_SOLID_Z_OFFSET_FORWARD:Ljava/util/function/Function;
       3: aload_0
       4: invokeinterface #111,  2          // InterfaceMethod java/util/function/Function.apply:(Ljava/lang/Object;)Ljava/lang/Object;
       9: checkcast     #113                // class net/minecraft/client/renderer/rendertype/RenderType
      12: areturn

  public static net.minecraft.client.renderer.rendertype.RenderType entityCutout(net.minecraft.resources.Identifier);
    Code:
       0: getstatic     #183                // Field ENTITY_CUTOUT:Ljava/util/function/Function;
       3: aload_0
       4: invokeinterface #111,  2          // InterfaceMethod java/util/function/Function.apply:(Ljava/lang/Object;)Ljava/lang/Object;
       9: checkcast     #113                // class net/minecraft/client/renderer/rendertype/RenderType
      12: areturn

  public static net.minecraft.client.renderer.rendertype.RenderType entityCutoutNoCull(net.minecraft.resources.Identifier, boolean);
    Code:
       0: getstatic     #188                // Field ENTITY_CUTOUT_NO_CULL:Ljava/util/function/BiFunction;
       3: aload_0
       4: iload_1
       5: invokestatic  #194                // Method java/lang/Boolean.valueOf:(Z)Ljava/lang/Boolean;
       8: invokeinterface #199,  3          // InterfaceMethod java/util/function/BiFunction.apply:(Ljava/lang/Object;Ljava/lang/Object;)Ljava/lang/Object;
      13: checkcast     #113                // class net/minecraft/client/renderer/rendertype/RenderType
      16: areturn

  public static net.minecraft.client.renderer.rendertype.RenderType entityCutoutNoCull(net.minecraft.resources.Identifier);
    Code:
       0: aload_0
       1: iconst_1
       2: invokestatic  #202                // Method entityCutoutNoCull:(Lnet/minecraft/resources/Identifier;Z)Lnet/minecraft/client/renderer/rendertype/RenderType;
       5: areturn

  public static net.minecraft.client.renderer.rendertype.RenderType entityCutoutNoCullZOffset(net.minecraft.resources.Identifier, boolean);
    Code:
       0: getstatic     #205                // Field ENTITY_CUTOUT_NO_CULL_Z_OFFSET:Ljava/util/function/BiFunction;
       3: aload_0
       4: iload_1
       5: invokestatic  #194                // Method java/lang/Boolean.valueOf:(Z)Ljava/lang/Boolean;
       8: invokeinterface #199,  3          // InterfaceMethod java/util/function/BiFunction.apply:(Ljava/lang/Object;Ljava/lang/Object;)Ljava/lang/Object;
      13: checkcast     #113                // class net/minecraft/client/renderer/rendertype/RenderType
      16: areturn

  public static net.minecraft.client.renderer.rendertype.RenderType entityCutoutNoCullZOffset(net.minecraft.resources.Identifier);
    Code:
       0: aload_0
       1: iconst_1
       2: invokestatic  #207                // Method entityCutoutNoCullZOffset:(Lnet/minecraft/resources/Identifier;Z)Lnet/minecraft/client/renderer/rendertype/RenderType;
       5: areturn

  public static net.minecraft.client.renderer.rendertype.RenderType itemEntityTranslucentCull(net.minecraft.resources.Identifier);
    Code:
       0: getstatic     #210                // Field ITEM_ENTITY_TRANSLUCENT_CULL:Ljava/util/function/Function;
       3: aload_0
       4: invokeinterface #111,  2          // InterfaceMethod java/util/function/Function.apply:(Ljava/lang/Object;)Ljava/lang/Object;
       9: checkcast     #113                // class net/minecraft/client/renderer/rendertype/RenderType
      12: areturn

  public static net.minecraft.client.renderer.rendertype.RenderType entityTranslucent(net.minecraft.resources.Identifier, boolean);
    Code:
       0: getstatic     #213                // Field ENTITY_TRANSLUCENT:Ljava/util/function/BiFunction;
       3: aload_0
       4: iload_1
       5: invokestatic  #194                // Method java/lang/Boolean.valueOf:(Z)Ljava/lang/Boolean;
       8: invokeinterface #199,  3          // InterfaceMethod java/util/function/BiFunction.apply:(Ljava/lang/Object;Ljava/lang/Object;)Ljava/lang/Object;
      13: checkcast     #113                // class net/minecraft/client/renderer/rendertype/RenderType
      16: areturn

  public static net.minecraft.client.renderer.rendertype.RenderType entityTranslucent(net.minecraft.resources.Identifier);
    Code:
       0: aload_0
       1: iconst_1
       2: invokestatic  #215                // Method entityTranslucent:(Lnet/minecraft/resources/Identifier;Z)Lnet/minecraft/client/renderer/rendertype/RenderType;
       5: areturn

  public static net.minecraft.client.renderer.rendertype.RenderType entityTranslucentEmissive(net.minecraft.resources.Identifier, boolean);
    Code:
       0: getstatic     #218                // Field ENTITY_TRANSLUCENT_EMISSIVE:Ljava/util/function/BiFunction;
       3: aload_0
       4: iload_1
       5: invokestatic  #194                // Method java/lang/Boolean.valueOf:(Z)Ljava/lang/Boolean;
       8: invokeinterface #199,  3          // InterfaceMethod java/util/function/BiFunction.apply:(Ljava/lang/Object;Ljava/lang/Object;)Ljava/lang/Object;
      13: checkcast     #113                // class net/minecraft/client/renderer/rendertype/RenderType
      16: areturn

  public static net.minecraft.client.renderer.rendertype.RenderType entityTranslucentEmissive(net.minecraft.resources.Identifier);
    Code:
       0: aload_0
       1: iconst_1
       2: invokestatic  #220                // Method entityTranslucentEmissive:(Lnet/minecraft/resources/Identifier;Z)Lnet/minecraft/client/renderer/rendertype/RenderType;
       5: areturn

  public static net.minecraft.client.renderer.rendertype.RenderType entitySmoothCutout(net.minecraft.resources.Identifier);
    Code:
       0: getstatic     #223                // Field ENTITY_SMOOTH_CUTOUT:Ljava/util/function/Function;
       3: aload_0
       4: invokeinterface #111,  2          // InterfaceMethod java/util/function/Function.apply:(Ljava/lang/Object;)Ljava/lang/Object;
       9: checkcast     #113                // class net/minecraft/client/renderer/rendertype/RenderType
      12: areturn

  public static net.minecraft.client.renderer.rendertype.RenderType beaconBeam(net.minecraft.resources.Identifier, boolean);
    Code:
       0: getstatic     #226                // Field BEACON_BEAM:Ljava/util/function/BiFunction;
       3: aload_0
       4: iload_1
       5: invokestatic  #194                // Method java/lang/Boolean.valueOf:(Z)Ljava/lang/Boolean;
       8: invokeinterface #199,  3          // InterfaceMethod java/util/function/BiFunction.apply:(Ljava/lang/Object;Ljava/lang/Object;)Ljava/lang/Object;
      13: checkcast     #113                // class net/minecraft/client/renderer/rendertype/RenderType
      16: areturn

  public static net.minecraft.client.renderer.rendertype.RenderType entityDecal(net.minecraft.resources.Identifier);
    Code:
       0: getstatic     #229                // Field ENTITY_DECAL:Ljava/util/function/Function;
       3: aload_0
       4: invokeinterface #111,  2          // InterfaceMethod java/util/function/Function.apply:(Ljava/lang/Object;)Ljava/lang/Object;
       9: checkcast     #113                // class net/minecraft/client/renderer/rendertype/RenderType
      12: areturn

  public static net.minecraft.client.renderer.rendertype.RenderType entityNoOutline(net.minecraft.resources.Identifier);
    Code:
       0: getstatic     #232                // Field ENTITY_NO_OUTLINE:Ljava/util/function/Function;
       3: aload_0
       4: invokeinterface #111,  2          // InterfaceMethod java/util/function/Function.apply:(Ljava/lang/Object;)Ljava/lang/Object;
       9: checkcast     #113                // class net/minecraft/client/renderer/rendertype/RenderType
      12: areturn

  public static net.minecraft.client.renderer.rendertype.RenderType entityShadow(net.minecraft.resources.Identifier);
    Code:
       0: getstatic     #235                // Field ENTITY_SHADOW:Ljava/util/function/Function;
       3: aload_0
       4: invokeinterface #111,  2          // InterfaceMethod java/util/function/Function.apply:(Ljava/lang/Object;)Ljava/lang/Object;
       9: checkcast     #113                // class net/minecraft/client/renderer/rendertype/RenderType
      12: areturn

  public static net.minecraft.client.renderer.rendertype.RenderType dragonExplosionAlpha(net.minecraft.resources.Identifier);
    Code:
       0: getstatic     #238                // Field DRAGON_EXPLOSION_ALPHA:Ljava/util/function/Function;
       3: aload_0
       4: invokeinterface #111,  2          // InterfaceMethod java/util/function/Function.apply:(Ljava/lang/Object;)Ljava/lang/Object;
       9: checkcast     #113                // class net/minecraft/client/renderer/rendertype/RenderType
      12: areturn

  public static net.minecraft.client.renderer.rendertype.RenderType eyes(net.minecraft.resources.Identifier);
    Code:
       0: getstatic     #241                // Field EYES:Ljava/util/function/Function;
       3: aload_0
       4: invokeinterface #111,  2          // InterfaceMethod java/util/function/Function.apply:(Ljava/lang/Object;)Ljava/lang/Object;
       9: checkcast     #113                // class net/minecraft/client/renderer/rendertype/RenderType
      12: areturn

  public static net.minecraft.client.renderer.rendertype.RenderType breezeEyes(net.minecraft.resources.Identifier);
    Code:
       0: getstatic     #218                // Field ENTITY_TRANSLUCENT_EMISSIVE:Ljava/util/function/BiFunction;
       3: aload_0
       4: iconst_0
       5: invokestatic  #194                // Method java/lang/Boolean.valueOf:(Z)Ljava/lang/Boolean;
       8: invokeinterface #199,  3          // InterfaceMethod java/util/function/BiFunction.apply:(Ljava/lang/Object;Ljava/lang/Object;)Ljava/lang/Object;
      13: checkcast     #113                // class net/minecraft/client/renderer/rendertype/RenderType
      16: areturn

  public static net.minecraft.client.renderer.rendertype.RenderType breezeWind(net.minecraft.resources.Identifier, float, float);
    Code:
       0: ldc           #248                // String breeze_wind
       2: getstatic     #251                // Field net/minecraft/client/renderer/RenderPipelines.BREEZE_WIND:Lcom/mojang/blaze3d/pipeline/RenderPipeline;
       5: invokestatic  #125                // Method net/minecraft/client/renderer/rendertype/RenderSetup.builder:(Lcom/mojang/blaze3d/pipeline/RenderPipeline;)Lnet/minecraft/client/renderer/rendertype/RenderSetup$RenderSetupBuilder;
       8: ldc           #127                // String Sampler0
      10: aload_0
      11: invokevirtual #131                // Method net/minecraft/client/renderer/rendertype/RenderSetup$RenderSetupBuilder.withTexture:(Ljava/lang/String;Lnet/minecraft/resources/Identifier;)Lnet/minecraft/client/renderer/rendertype/RenderSetup$RenderSetupBuilder;
      14: new           #15                 // class net/minecraft/client/renderer/rendertype/TextureTransform$OffsetTextureTransform
      17: dup
      18: fload_1
      19: fload_2
      20: invokespecial #254                // Method net/minecraft/client/renderer/rendertype/TextureTransform$OffsetTextureTransform."<init>":(FF)V
      23: invokevirtual #258                // Method net/minecraft/client/renderer/rendertype/RenderSetup$RenderSetupBuilder.setTextureTransform:(Lnet/minecraft/client/renderer/rendertype/TextureTransform;)Lnet/minecraft/client/renderer/rendertype/RenderSetup$RenderSetupBuilder;
      26: invokevirtual #135                // Method net/minecraft/client/renderer/rendertype/RenderSetup$RenderSetupBuilder.useLightmap:()Lnet/minecraft/client/renderer/rendertype/RenderSetup$RenderSetupBuilder;
      29: invokevirtual #261                // Method net/minecraft/client/renderer/rendertype/RenderSetup$RenderSetupBuilder.sortOnUpload:()Lnet/minecraft/client/renderer/rendertype/RenderSetup$RenderSetupBuilder;
      32: invokevirtual #163                // Method net/minecraft/client/renderer/rendertype/RenderSetup$RenderSetupBuilder.createRenderSetup:()Lnet/minecraft/client/renderer/rendertype/RenderSetup;
      35: invokestatic  #169                // Method net/minecraft/client/renderer/rendertype/RenderType.create:(Ljava/lang/String;Lnet/minecraft/client/renderer/rendertype/RenderSetup;)Lnet/minecraft/client/renderer/rendertype/RenderType;
      38: areturn

  public static net.minecraft.client.renderer.rendertype.RenderType energySwirl(net.minecraft.resources.Identifier, float, float);
    Code:
       0: ldc_w         #265                // String energy_swirl
       3: getstatic     #268                // Field net/minecraft/client/renderer/RenderPipelines.ENERGY_SWIRL:Lcom/mojang/blaze3d/pipeline/RenderPipeline;
       6: invokestatic  #125                // Method net/minecraft/client/renderer/rendertype/RenderSetup.builder:(Lcom/mojang/blaze3d/pipeline/RenderPipeline;)Lnet/minecraft/client/renderer/rendertype/RenderSetup$RenderSetupBuilder;
       9: ldc           #127                // String Sampler0
      11: aload_0
      12: invokevirtual #131                // Method net/minecraft/client/renderer/rendertype/RenderSetup$RenderSetupBuilder.withTexture:(Ljava/lang/String;Lnet/minecraft/resources/Identifier;)Lnet/minecraft/client/renderer/rendertype/RenderSetup$RenderSetupBuilder;
      15: new           #15                 // class net/minecraft/client/renderer/rendertype/TextureTransform$OffsetTextureTransform
      18: dup
      19: fload_1
      20: fload_2
      21: invokespecial #254                // Method net/minecraft/client/renderer/rendertype/TextureTransform$OffsetTextureTransform."<init>":(FF)V
      24: invokevirtual #258                // Method net/minecraft/client/renderer/rendertype/RenderSetup$RenderSetupBuilder.setTextureTransform:(Lnet/minecraft/client/renderer/rendertype/TextureTransform;)Lnet/minecraft/client/renderer/rendertype/RenderSetup$RenderSetupBuilder;
      27: invokevirtual #135                // Method net/minecraft/client/renderer/rendertype/RenderSetup$RenderSetupBuilder.useLightmap:()Lnet/minecraft/client/renderer/rendertype/RenderSetup$RenderSetupBuilder;
      30: invokevirtual #138                // Method net/minecraft/client/renderer/rendertype/RenderSetup$RenderSetupBuilder.useOverlay:()Lnet/minecraft/client/renderer/rendertype/RenderSetup$RenderSetupBuilder;
      33: invokevirtual #261                // Method net/minecraft/client/renderer/rendertype/RenderSetup$RenderSetupBuilder.sortOnUpload:()Lnet/minecraft/client/renderer/rendertype/RenderSetup$RenderSetupBuilder;
      36: invokevirtual #163                // Method net/minecraft/client/renderer/rendertype/RenderSetup$RenderSetupBuilder.createRenderSetup:()Lnet/minecraft/client/renderer/rendertype/RenderSetup;
      39: invokestatic  #169                // Method net/minecraft/client/renderer/rendertype/RenderType.create:(Ljava/lang/String;Lnet/minecraft/client/renderer/rendertype/RenderSetup;)Lnet/minecraft/client/renderer/rendertype/RenderType;
      42: areturn

  public static net.minecraft.client.renderer.rendertype.RenderType leash();
    Code:
       0: getstatic     #271                // Field LEASH:Lnet/minecraft/client/renderer/rendertype/RenderType;
       3: areturn

  public static net.minecraft.client.renderer.rendertype.RenderType waterMask();
    Code:
       0: getstatic     #274                // Field WATER_MASK:Lnet/minecraft/client/renderer/rendertype/RenderType;
       3: areturn

  public static net.minecraft.client.renderer.rendertype.RenderType outline(net.minecraft.resources.Identifier);
    Code:
       0: getstatic     #277                // Field OUTLINE:Ljava/util/function/BiFunction;
       3: aload_0
       4: iconst_0
       5: invokestatic  #194                // Method java/lang/Boolean.valueOf:(Z)Ljava/lang/Boolean;
       8: invokeinterface #199,  3          // InterfaceMethod java/util/function/BiFunction.apply:(Ljava/lang/Object;Ljava/lang/Object;)Ljava/lang/Object;
      13: checkcast     #113                // class net/minecraft/client/renderer/rendertype/RenderType
      16: areturn

  public static net.minecraft.client.renderer.rendertype.RenderType armorEntityGlint();
    Code:
       0: getstatic     #280                // Field ARMOR_ENTITY_GLINT:Lnet/minecraft/client/renderer/rendertype/RenderType;
       3: areturn

  public static net.minecraft.client.renderer.rendertype.RenderType glintTranslucent();
    Code:
       0: getstatic     #283                // Field GLINT_TRANSLUCENT:Lnet/minecraft/client/renderer/rendertype/RenderType;
       3: areturn

  public static net.minecraft.client.renderer.rendertype.RenderType glint();
    Code:
       0: getstatic     #286                // Field GLINT:Lnet/minecraft/client/renderer/rendertype/RenderType;
       3: areturn

  public static net.minecraft.client.renderer.rendertype.RenderType entityGlint();
    Code:
       0: getstatic     #289                // Field ENTITY_GLINT:Lnet/minecraft/client/renderer/rendertype/RenderType;
       3: areturn

  public static net.minecraft.client.renderer.rendertype.RenderType crumbling(net.minecraft.resources.Identifier);
    Code:
       0: getstatic     #292                // Field CRUMBLING:Ljava/util/function/Function;
       3: aload_0
       4: invokeinterface #111,  2          // InterfaceMethod java/util/function/Function.apply:(Ljava/lang/Object;)Ljava/lang/Object;
       9: checkcast     #113                // class net/minecraft/client/renderer/rendertype/RenderType
      12: areturn

  public static net.minecraft.client.renderer.rendertype.RenderType text(net.minecraft.resources.Identifier);
    Code:
       0: getstatic     #295                // Field TEXT:Ljava/util/function/Function;
       3: aload_0
       4: invokeinterface #111,  2          // InterfaceMethod java/util/function/Function.apply:(Ljava/lang/Object;)Ljava/lang/Object;
       9: checkcast     #113                // class net/minecraft/client/renderer/rendertype/RenderType
      12: areturn

  public static net.minecraft.client.renderer.rendertype.RenderType textBackground();
    Code:
       0: getstatic     #298                // Field TEXT_BACKGROUND:Lnet/minecraft/client/renderer/rendertype/RenderType;
       3: areturn

  public static net.minecraft.client.renderer.rendertype.RenderType textIntensity(net.minecraft.resources.Identifier);
    Code:
       0: getstatic     #301                // Field TEXT_INTENSITY:Ljava/util/function/Function;
       3: aload_0
       4: invokeinterface #111,  2          // InterfaceMethod java/util/function/Function.apply:(Ljava/lang/Object;)Ljava/lang/Object;
       9: checkcast     #113                // class net/minecraft/client/renderer/rendertype/RenderType
      12: areturn

  public static net.minecraft.client.renderer.rendertype.RenderType textPolygonOffset(net.minecraft.resources.Identifier);
    Code:
       0: getstatic     #304                // Field TEXT_POLYGON_OFFSET:Ljava/util/function/Function;
       3: aload_0
       4: invokeinterface #111,  2          // InterfaceMethod java/util/function/Function.apply:(Ljava/lang/Object;)Ljava/lang/Object;
       9: checkcast     #113                // class net/minecraft/client/renderer/rendertype/RenderType
      12: areturn

  public static net.minecraft.client.renderer.rendertype.RenderType textIntensityPolygonOffset(net.minecraft.resources.Identifier);
    Code:
       0: getstatic     #307                // Field TEXT_INTENSITY_POLYGON_OFFSET:Ljava/util/function/Function;
       3: aload_0
       4: invokeinterface #111,  2          // InterfaceMethod java/util/function/Function.apply:(Ljava/lang/Object;)Ljava/lang/Object;
       9: checkcast     #113                // class net/minecraft/client/renderer/rendertype/RenderType
      12: areturn

  public static net.minecraft.client.renderer.rendertype.RenderType textSeeThrough(net.minecraft.resources.Identifier);
    Code:
       0: getstatic     #310                // Field TEXT_SEE_THROUGH:Ljava/util/function/Function;
       3: aload_0
       4: invokeinterface #111,  2          // InterfaceMethod java/util/function/Function.apply:(Ljava/lang/Object;)Ljava/lang/Object;
       9: checkcast     #113                // class net/minecraft/client/renderer/rendertype/RenderType
      12: areturn

  public static net.minecraft.client.renderer.rendertype.RenderType textBackgroundSeeThrough();
    Code:
       0: getstatic     #313                // Field TEXT_BACKGROUND_SEE_THROUGH:Lnet/minecraft/client/renderer/rendertype/RenderType;
       3: areturn

  public static net.minecraft.client.renderer.rendertype.RenderType textIntensitySeeThrough(net.minecraft.resources.Identifier);
    Code:
       0: getstatic     #316                // Field TEXT_INTENSITY_SEE_THROUGH:Ljava/util/function/Function;
       3: aload_0
       4: invokeinterface #111,  2          // InterfaceMethod java/util/function/Function.apply:(Ljava/lang/Object;)Ljava/lang/Object;
       9: checkcast     #113                // class net/minecraft/client/renderer/rendertype/RenderType
      12: areturn

  public static net.minecraft.client.renderer.rendertype.RenderType lightning();
    Code:
       0: getstatic     #319                // Field LIGHTNING:Lnet/minecraft/client/renderer/rendertype/RenderType;
       3: areturn

  public static net.minecraft.client.renderer.rendertype.RenderType dragonRays();
    Code:
       0: getstatic     #322                // Field DRAGON_RAYS:Lnet/minecraft/client/renderer/rendertype/RenderType;
       3: areturn

  public static net.minecraft.client.renderer.rendertype.RenderType dragonRaysDepth();
    Code:
       0: getstatic     #325                // Field DRAGON_RAYS_DEPTH:Lnet/minecraft/client/renderer/rendertype/RenderType;
       3: areturn

  public static net.minecraft.client.renderer.rendertype.RenderType tripwireMovingBlock();
    Code:
       0: getstatic     #328                // Field TRIPWIRE_MOVING_BLOCk:Lnet/minecraft/client/renderer/rendertype/RenderType;
       3: areturn

  public static net.minecraft.client.renderer.rendertype.RenderType endPortal();
    Code:
       0: getstatic     #331                // Field END_PORTAL:Lnet/minecraft/client/renderer/rendertype/RenderType;
       3: areturn

  public static net.minecraft.client.renderer.rendertype.RenderType endGateway();
    Code:
       0: getstatic     #334                // Field END_GATEWAY:Lnet/minecraft/client/renderer/rendertype/RenderType;
       3: areturn

  public static net.minecraft.client.renderer.rendertype.RenderType lines();
    Code:
       0: getstatic     #337                // Field LINES:Lnet/minecraft/client/renderer/rendertype/RenderType;
       3: areturn

  public static net.minecraft.client.renderer.rendertype.RenderType linesTranslucent();
    Code:
       0: getstatic     #340                // Field LINES_TRANSLUCENT:Lnet/minecraft/client/renderer/rendertype/RenderType;
       3: areturn

  public static net.minecraft.client.renderer.rendertype.RenderType secondaryBlockOutline();
    Code:
       0: getstatic     #343                // Field SECONDARY_BLOCK_OUTLINE:Lnet/minecraft/client/renderer/rendertype/RenderType;
       3: areturn

  public static net.minecraft.client.renderer.rendertype.RenderType debugFilledBox();
    Code:
       0: getstatic     #346                // Field DEBUG_FILLED_BOX:Lnet/minecraft/client/renderer/rendertype/RenderType;
       3: areturn

  public static net.minecraft.client.renderer.rendertype.RenderType debugPoint();
    Code:
       0: getstatic     #349                // Field DEBUG_POINT:Lnet/minecraft/client/renderer/rendertype/RenderType;
       3: areturn

  public static net.minecraft.client.renderer.rendertype.RenderType debugQuads();
    Code:
       0: getstatic     #352                // Field DEBUG_QUADS:Lnet/minecraft/client/renderer/rendertype/RenderType;
       3: areturn

  public static net.minecraft.client.renderer.rendertype.RenderType debugTriangleFan();
    Code:
       0: getstatic     #355                // Field DEBUG_TRIANGLE_FAN:Lnet/minecraft/client/renderer/rendertype/RenderType;
       3: areturn

  private static java.util.function.Function<net.minecraft.resources.Identifier, net.minecraft.client.renderer.rendertype.RenderType> createWeather(com.mojang.blaze3d.pipeline.RenderPipeline);
    Code:
       0: aload_0
       1: invokedynamic #375,  0            // InvokeDynamic #0:apply:(Lcom/mojang/blaze3d/pipeline/RenderPipeline;)Ljava/util/function/Function;
       6: invokestatic  #381                // Method net/minecraft/util/Util.memoize:(Ljava/util/function/Function;)Ljava/util/function/Function;
       9: areturn

  public static net.minecraft.client.renderer.rendertype.RenderType weather(net.minecraft.resources.Identifier, boolean);
    Code:
       0: iload_1
       1: ifeq          10
       4: getstatic     #384                // Field WEATHER_DEPTH_WRITE:Ljava/util/function/Function;
       7: goto          13
      10: getstatic     #386                // Field WEATHER_NO_DEPTH_WRITE:Ljava/util/function/Function;
      13: aload_0
      14: invokeinterface #111,  2          // InterfaceMethod java/util/function/Function.apply:(Ljava/lang/Object;)Ljava/lang/Object;
      19: checkcast     #113                // class net/minecraft/client/renderer/rendertype/RenderType
      22: areturn

  public static net.minecraft.client.renderer.rendertype.RenderType blockScreenEffect(net.minecraft.resources.Identifier);
    Code:
       0: getstatic     #389                // Field BLOCK_SCREEN_EFFECT:Ljava/util/function/Function;
       3: aload_0
       4: invokeinterface #111,  2          // InterfaceMethod java/util/function/Function.apply:(Ljava/lang/Object;)Ljava/lang/Object;
       9: checkcast     #113                // class net/minecraft/client/renderer/rendertype/RenderType
      12: areturn

  public static net.minecraft.client.renderer.rendertype.RenderType fireScreenEffect(net.minecraft.resources.Identifier);
    Code:
       0: getstatic     #392                // Field FIRE_SCREEN_EFFECT:Ljava/util/function/Function;
       3: aload_0
       4: invokeinterface #111,  2          // InterfaceMethod java/util/function/Function.apply:(Ljava/lang/Object;)Ljava/lang/Object;
       9: checkcast     #113                // class net/minecraft/client/renderer/rendertype/RenderType
      12: areturn

  private static net.minecraft.client.renderer.rendertype.RenderType method_75944(net.minecraft.resources.Identifier);
    Code:
       0: ldc_w         #395                // String fire_screen_effect
       3: getstatic     #397                // Field net/minecraft/client/renderer/RenderPipelines.FIRE_SCREEN_EFFECT:Lcom/mojang/blaze3d/pipeline/RenderPipeline;
       6: invokestatic  #125                // Method net/minecraft/client/renderer/rendertype/RenderSetup.builder:(Lcom/mojang/blaze3d/pipeline/RenderPipeline;)Lnet/minecraft/client/renderer/rendertype/RenderSetup$RenderSetupBuilder;
       9: ldc           #127                // String Sampler0
      11: aload_0
      12: invokevirtual #131                // Method net/minecraft/client/renderer/rendertype/RenderSetup$RenderSetupBuilder.withTexture:(Ljava/lang/String;Lnet/minecraft/resources/Identifier;)Lnet/minecraft/client/renderer/rendertype/RenderSetup$RenderSetupBuilder;
      15: invokevirtual #163                // Method net/minecraft/client/renderer/rendertype/RenderSetup$RenderSetupBuilder.createRenderSetup:()Lnet/minecraft/client/renderer/rendertype/RenderSetup;
      18: invokestatic  #169                // Method net/minecraft/client/renderer/rendertype/RenderType.create:(Ljava/lang/String;Lnet/minecraft/client/renderer/rendertype/RenderSetup;)Lnet/minecraft/client/renderer/rendertype/RenderType;
      21: areturn

  private static net.minecraft.client.renderer.rendertype.RenderType method_75945(net.minecraft.resources.Identifier);
    Code:
       0: ldc_w         #400                // String block_screen_effect
       3: getstatic     #402                // Field net/minecraft/client/renderer/RenderPipelines.BLOCK_SCREEN_EFFECT:Lcom/mojang/blaze3d/pipeline/RenderPipeline;
       6: invokestatic  #125                // Method net/minecraft/client/renderer/rendertype/RenderSetup.builder:(Lcom/mojang/blaze3d/pipeline/RenderPipeline;)Lnet/minecraft/client/renderer/rendertype/RenderSetup$RenderSetupBuilder;
       9: ldc           #127                // String Sampler0
      11: aload_0
      12: invokevirtual #131                // Method net/minecraft/client/renderer/rendertype/RenderSetup$RenderSetupBuilder.withTexture:(Ljava/lang/String;Lnet/minecraft/resources/Identifier;)Lnet/minecraft/client/renderer/rendertype/RenderSetup$RenderSetupBuilder;
      15: invokevirtual #163                // Method net/minecraft/client/renderer/rendertype/RenderSetup$RenderSetupBuilder.createRenderSetup:()Lnet/minecraft/client/renderer/rendertype/RenderSetup;
      18: invokestatic  #169                // Method net/minecraft/client/renderer/rendertype/RenderType.create:(Ljava/lang/String;Lnet/minecraft/client/renderer/rendertype/RenderSetup;)Lnet/minecraft/client/renderer/rendertype/RenderType;
      21: areturn

  private static net.minecraft.client.renderer.rendertype.RenderType method_75971(com.mojang.blaze3d.pipeline.RenderPipeline, net.minecraft.resources.Identifier);
    Code:
       0: ldc_w         #403                // String weather
       3: aload_0
       4: invokestatic  #125                // Method net/minecraft/client/renderer/rendertype/RenderSetup.builder:(Lcom/mojang/blaze3d/pipeline/RenderPipeline;)Lnet/minecraft/client/renderer/rendertype/RenderSetup$RenderSetupBuilder;
       7: ldc           #127                // String Sampler0
       9: aload_1
      10: invokevirtual #131                // Method net/minecraft/client/renderer/rendertype/RenderSetup$RenderSetupBuilder.withTexture:(Ljava/lang/String;Lnet/minecraft/resources/Identifier;)Lnet/minecraft/client/renderer/rendertype/RenderSetup$RenderSetupBuilder;
      13: getstatic     #409                // Field net/minecraft/client/renderer/rendertype/OutputTarget.WEATHER_TARGET:Lnet/minecraft/client/renderer/rendertype/OutputTarget;
      16: invokevirtual #413                // Method net/minecraft/client/renderer/rendertype/RenderSetup$RenderSetupBuilder.setOutputTarget:(Lnet/minecraft/client/renderer/rendertype/OutputTarget;)Lnet/minecraft/client/renderer/rendertype/RenderSetup$RenderSetupBuilder;
      19: invokevirtual #135                // Method net/minecraft/client/renderer/rendertype/RenderSetup$RenderSetupBuilder.useLightmap:()Lnet/minecraft/client/renderer/rendertype/RenderSetup$RenderSetupBuilder;
      22: invokevirtual #163                // Method net/minecraft/client/renderer/rendertype/RenderSetup$RenderSetupBuilder.createRenderSetup:()Lnet/minecraft/client/renderer/rendertype/RenderSetup;
      25: invokestatic  #169                // Method net/minecraft/client/renderer/rendertype/RenderType.create:(Ljava/lang/String;Lnet/minecraft/client/renderer/rendertype/RenderSetup;)Lnet/minecraft/client/renderer/rendertype/RenderType;
      28: areturn

  private static net.minecraft.client.renderer.rendertype.RenderType method_75946(net.minecraft.resources.Identifier);
    Code:
       0: ldc_w         #416                // String text_intensity_see_through
       3: getstatic     #418                // Field net/minecraft/client/renderer/RenderPipelines.TEXT_INTENSITY_SEE_THROUGH:Lcom/mojang/blaze3d/pipeline/RenderPipeline;
       6: invokestatic  #125                // Method net/minecraft/client/renderer/rendertype/RenderSetup.builder:(Lcom/mojang/blaze3d/pipeline/RenderPipeline;)Lnet/minecraft/client/renderer/rendertype/RenderSetup$RenderSetupBuilder;
       9: ldc           #127                // String Sampler0
      11: aload_0
      12: invokevirtual #131                // Method net/minecraft/client/renderer/rendertype/RenderSetup$RenderSetupBuilder.withTexture:(Ljava/lang/String;Lnet/minecraft/resources/Identifier;)Lnet/minecraft/client/renderer/rendertype/RenderSetup$RenderSetupBuilder;
      15: invokevirtual #135                // Method net/minecraft/client/renderer/rendertype/RenderSetup$RenderSetupBuilder.useLightmap:()Lnet/minecraft/client/renderer/rendertype/RenderSetup$RenderSetupBuilder;
      18: invokevirtual #261                // Method net/minecraft/client/renderer/rendertype/RenderSetup$RenderSetupBuilder.sortOnUpload:()Lnet/minecraft/client/renderer/rendertype/RenderSetup$RenderSetupBuilder;
      21: invokevirtual #163                // Method net/minecraft/client/renderer/rendertype/RenderSetup$RenderSetupBuilder.createRenderSetup:()Lnet/minecraft/client/renderer/rendertype/RenderSetup;
      24: invokestatic  #169                // Method net/minecraft/client/renderer/rendertype/RenderType.create:(Ljava/lang/String;Lnet/minecraft/client/renderer/rendertype/RenderSetup;)Lnet/minecraft/client/renderer/rendertype/RenderType;
      27: areturn

  private static net.minecraft.client.renderer.rendertype.RenderType method_75947(net.minecraft.resources.Identifier);
    Code:
       0: ldc_w         #421                // String text_see_through
       3: getstatic     #423                // Field net/minecraft/client/renderer/RenderPipelines.TEXT_SEE_THROUGH:Lcom/mojang/blaze3d/pipeline/RenderPipeline;
       6: invokestatic  #125                // Method net/minecraft/client/renderer/rendertype/RenderSetup.builder:(Lcom/mojang/blaze3d/pipeline/RenderPipeline;)Lnet/minecraft/client/renderer/rendertype/RenderSetup$RenderSetupBuilder;
       9: ldc           #127                // String Sampler0
      11: aload_0
      12: invokevirtual #131                // Method net/minecraft/client/renderer/rendertype/RenderSetup$RenderSetupBuilder.withTexture:(Ljava/lang/String;Lnet/minecraft/resources/Identifier;)Lnet/minecraft/client/renderer/rendertype/RenderSetup$RenderSetupBuilder;
      15: invokevirtual #135                // Method net/minecraft/client/renderer/rendertype/RenderSetup$RenderSetupBuilder.useLightmap:()Lnet/minecraft/client/renderer/rendertype/RenderSetup$RenderSetupBuilder;
      18: invokevirtual #163                // Method net/minecraft/client/renderer/rendertype/RenderSetup$RenderSetupBuilder.createRenderSetup:()Lnet/minecraft/client/renderer/rendertype/RenderSetup;
      21: invokestatic  #169                // Method net/minecraft/client/renderer/rendertype/RenderType.create:(Ljava/lang/String;Lnet/minecraft/client/renderer/rendertype/RenderSetup;)Lnet/minecraft/client/renderer/rendertype/RenderType;
      24: areturn

  private static net.minecraft.client.renderer.rendertype.RenderType method_75948(net.minecraft.resources.Identifier);
    Code:
       0: ldc_w         #426                // String text_intensity_polygon_offset
       3: getstatic     #428                // Field net/minecraft/client/renderer/RenderPipelines.TEXT_INTENSITY:Lcom/mojang/blaze3d/pipeline/RenderPipeline;
       6: invokestatic  #125                // Method net/minecraft/client/renderer/rendertype/RenderSetup.builder:(Lcom/mojang/blaze3d/pipeline/RenderPipeline;)Lnet/minecraft/client/renderer/rendertype/RenderSetup$RenderSetupBuilder;
       9: ldc           #127                // String Sampler0
      11: aload_0
      12: invokevirtual #131                // Method net/minecraft/client/renderer/rendertype/RenderSetup$RenderSetupBuilder.withTexture:(Ljava/lang/String;Lnet/minecraft/resources/Identifier;)Lnet/minecraft/client/renderer/rendertype/RenderSetup$RenderSetupBuilder;
      15: invokevirtual #135                // Method net/minecraft/client/renderer/rendertype/RenderSetup$RenderSetupBuilder.useLightmap:()Lnet/minecraft/client/renderer/rendertype/RenderSetup$RenderSetupBuilder;
      18: invokevirtual #261                // Method net/minecraft/client/renderer/rendertype/RenderSetup$RenderSetupBuilder.sortOnUpload:()Lnet/minecraft/client/renderer/rendertype/RenderSetup$RenderSetupBuilder;
      21: invokevirtual #163                // Method net/minecraft/client/renderer/rendertype/RenderSetup$RenderSetupBuilder.createRenderSetup:()Lnet/minecraft/client/renderer/rendertype/RenderSetup;
      24: invokestatic  #169                // Method net/minecraft/client/renderer/rendertype/RenderType.create:(Ljava/lang/String;Lnet/minecraft/client/renderer/rendertype/RenderSetup;)Lnet/minecraft/client/renderer/rendertype/RenderType;
      27: areturn

  private static net.minecraft.client.renderer.rendertype.RenderType method_75949(net.minecraft.resources.Identifier);
    Code:
       0: ldc_w         #431                // String text_polygon_offset
       3: getstatic     #433                // Field net/minecraft/client/renderer/RenderPipelines.TEXT_POLYGON_OFFSET:Lcom/mojang/blaze3d/pipeline/RenderPipeline;
       6: invokestatic  #125                // Method net/minecraft/client/renderer/rendertype/RenderSetup.builder:(Lcom/mojang/blaze3d/pipeline/RenderPipeline;)Lnet/minecraft/client/renderer/rendertype/RenderSetup$RenderSetupBuilder;
       9: ldc           #127                // String Sampler0
      11: aload_0
      12: invokevirtual #131                // Method net/minecraft/client/renderer/rendertype/RenderSetup$RenderSetupBuilder.withTexture:(Ljava/lang/String;Lnet/minecraft/resources/Identifier;)Lnet/minecraft/client/renderer/rendertype/RenderSetup$RenderSetupBuilder;
      15: invokevirtual #135                // Method net/minecraft/client/renderer/rendertype/RenderSetup$RenderSetupBuilder.useLightmap:()Lnet/minecraft/client/renderer/rendertype/RenderSetup$RenderSetupBuilder;
      18: invokevirtual #261                // Method net/minecraft/client/renderer/rendertype/RenderSetup$RenderSetupBuilder.sortOnUpload:()Lnet/minecraft/client/renderer/rendertype/RenderSetup$RenderSetupBuilder;
      21: invokevirtual #163                // Method net/minecraft/client/renderer/rendertype/RenderSetup$RenderSetupBuilder.createRenderSetup:()Lnet/minecraft/client/renderer/rendertype/RenderSetup;
      24: invokestatic  #169                // Method net/minecraft/client/renderer/rendertype/RenderType.create:(Ljava/lang/String;Lnet/minecraft/client/renderer/rendertype/RenderSetup;)Lnet/minecraft/client/renderer/rendertype/RenderType;
      27: areturn

  private static net.minecraft.client.renderer.rendertype.RenderType method_75950(net.minecraft.resources.Identifier);
    Code:
       0: ldc_w         #436                // String text_intensity
       3: getstatic     #428                // Field net/minecraft/client/renderer/RenderPipelines.TEXT_INTENSITY:Lcom/mojang/blaze3d/pipeline/RenderPipeline;
       6: invokestatic  #125                // Method net/minecraft/client/renderer/rendertype/RenderSetup.builder:(Lcom/mojang/blaze3d/pipeline/RenderPipeline;)Lnet/minecraft/client/renderer/rendertype/RenderSetup$RenderSetupBuilder;
       9: ldc           #127                // String Sampler0
      11: aload_0
      12: invokevirtual #131                // Method net/minecraft/client/renderer/rendertype/RenderSetup$RenderSetupBuilder.withTexture:(Ljava/lang/String;Lnet/minecraft/resources/Identifier;)Lnet/minecraft/client/renderer/rendertype/RenderSetup$RenderSetupBuilder;
      15: invokevirtual #135                // Method net/minecraft/client/renderer/rendertype/RenderSetup$RenderSetupBuilder.useLightmap:()Lnet/minecraft/client/renderer/rendertype/RenderSetup$RenderSetupBuilder;
      18: ldc_w         #437                // int 786432
      21: invokevirtual #441                // Method net/minecraft/client/renderer/rendertype/RenderSetup$RenderSetupBuilder.bufferSize:(I)Lnet/minecraft/client/renderer/rendertype/RenderSetup$RenderSetupBuilder;
      24: invokevirtual #163                // Method net/minecraft/client/renderer/rendertype/RenderSetup$RenderSetupBuilder.createRenderSetup:()Lnet/minecraft/client/renderer/rendertype/RenderSetup;
      27: invokestatic  #169                // Method net/minecraft/client/renderer/rendertype/RenderType.create:(Ljava/lang/String;Lnet/minecraft/client/renderer/rendertype/RenderSetup;)Lnet/minecraft/client/renderer/rendertype/RenderType;
      30: areturn

  private static net.minecraft.client.renderer.rendertype.RenderType method_75951(net.minecraft.resources.Identifier);
    Code:
       0: ldc_w         #443                // String text
       3: getstatic     #445                // Field net/minecraft/client/renderer/RenderPipelines.TEXT:Lcom/mojang/blaze3d/pipeline/RenderPipeline;
       6: invokestatic  #125                // Method net/minecraft/client/renderer/rendertype/RenderSetup.builder:(Lcom/mojang/blaze3d/pipeline/RenderPipeline;)Lnet/minecraft/client/renderer/rendertype/RenderSetup$RenderSetupBuilder;
       9: ldc           #127                // String Sampler0
      11: aload_0
      12: invokevirtual #131                // Method net/minecraft/client/renderer/rendertype/RenderSetup$RenderSetupBuilder.withTexture:(Ljava/lang/String;Lnet/minecraft/resources/Identifier;)Lnet/minecraft/client/renderer/rendertype/RenderSetup$RenderSetupBuilder;
      15: invokevirtual #135                // Method net/minecraft/client/renderer/rendertype/RenderSetup$RenderSetupBuilder.useLightmap:()Lnet/minecraft/client/renderer/rendertype/RenderSetup$RenderSetupBuilder;
      18: ldc_w         #437                // int 786432
      21: invokevirtual #441                // Method net/minecraft/client/renderer/rendertype/RenderSetup$RenderSetupBuilder.bufferSize:(I)Lnet/minecraft/client/renderer/rendertype/RenderSetup$RenderSetupBuilder;
      24: invokevirtual #163                // Method net/minecraft/client/renderer/rendertype/RenderSetup$RenderSetupBuilder.createRenderSetup:()Lnet/minecraft/client/renderer/rendertype/RenderSetup;
      27: invokestatic  #169                // Method net/minecraft/client/renderer/rendertype/RenderType.create:(Ljava/lang/String;Lnet/minecraft/client/renderer/rendertype/RenderSetup;)Lnet/minecraft/client/renderer/rendertype/RenderType;
      30: areturn

  private static net.minecraft.client.renderer.rendertype.RenderType method_75952(net.minecraft.resources.Identifier);
    Code:
       0: ldc_w         #447                // String crumbling
       3: getstatic     #449                // Field net/minecraft/client/renderer/RenderPipelines.CRUMBLING:Lcom/mojang/blaze3d/pipeline/RenderPipeline;
       6: invokestatic  #125                // Method net/minecraft/client/renderer/rendertype/RenderSetup.builder:(Lcom/mojang/blaze3d/pipeline/RenderPipeline;)Lnet/minecraft/client/renderer/rendertype/RenderSetup$RenderSetupBuilder;
       9: ldc           #127                // String Sampler0
      11: aload_0
      12: invokevirtual #131                // Method net/minecraft/client/renderer/rendertype/RenderSetup$RenderSetupBuilder.withTexture:(Ljava/lang/String;Lnet/minecraft/resources/Identifier;)Lnet/minecraft/client/renderer/rendertype/RenderSetup$RenderSetupBuilder;
      15: invokevirtual #261                // Method net/minecraft/client/renderer/rendertype/RenderSetup$RenderSetupBuilder.sortOnUpload:()Lnet/minecraft/client/renderer/rendertype/RenderSetup$RenderSetupBuilder;
      18: invokevirtual #163                // Method net/minecraft/client/renderer/rendertype/RenderSetup$RenderSetupBuilder.createRenderSetup:()Lnet/minecraft/client/renderer/rendertype/RenderSetup;
      21: invokestatic  #169                // Method net/minecraft/client/renderer/rendertype/RenderType.create:(Ljava/lang/String;Lnet/minecraft/client/renderer/rendertype/RenderSetup;)Lnet/minecraft/client/renderer/rendertype/RenderType;
      24: areturn

  private static net.minecraft.client.renderer.rendertype.RenderType method_75953(net.minecraft.resources.Identifier);
    Code:
       0: ldc_w         #451                // String eyes
       3: getstatic     #453                // Field net/minecraft/client/renderer/RenderPipelines.EYES:Lcom/mojang/blaze3d/pipeline/RenderPipeline;
       6: invokestatic  #125                // Method net/minecraft/client/renderer/rendertype/RenderSetup.builder:(Lcom/mojang/blaze3d/pipeline/RenderPipeline;)Lnet/minecraft/client/renderer/rendertype/RenderSetup$RenderSetupBuilder;
       9: ldc           #127                // String Sampler0
      11: aload_0
      12: invokevirtual #131                // Method net/minecraft/client/renderer/rendertype/RenderSetup$RenderSetupBuilder.withTexture:(Ljava/lang/String;Lnet/minecraft/resources/Identifier;)Lnet/minecraft/client/renderer/rendertype/RenderSetup$RenderSetupBuilder;
      15: invokevirtual #261                // Method net/minecraft/client/renderer/rendertype/RenderSetup$RenderSetupBuilder.sortOnUpload:()Lnet/minecraft/client/renderer/rendertype/RenderSetup$RenderSetupBuilder;
      18: invokevirtual #163                // Method net/minecraft/client/renderer/rendertype/RenderSetup$RenderSetupBuilder.createRenderSetup:()Lnet/minecraft/client/renderer/rendertype/RenderSetup;
      21: invokestatic  #169                // Method net/minecraft/client/renderer/rendertype/RenderType.create:(Ljava/lang/String;Lnet/minecraft/client/renderer/rendertype/RenderSetup;)Lnet/minecraft/client/renderer/rendertype/RenderType;
      24: areturn

  private static net.minecraft.client.renderer.rendertype.RenderType method_75954(net.minecraft.resources.Identifier);
    Code:
       0: getstatic     #456                // Field net/minecraft/client/renderer/RenderPipelines.DRAGON_EXPLOSION_ALPHA:Lcom/mojang/blaze3d/pipeline/RenderPipeline;
       3: invokestatic  #125                // Method net/minecraft/client/renderer/rendertype/RenderSetup.builder:(Lcom/mojang/blaze3d/pipeline/RenderPipeline;)Lnet/minecraft/client/renderer/rendertype/RenderSetup$RenderSetupBuilder;
       6: ldc           #127                // String Sampler0
       8: aload_0
       9: invokevirtual #131                // Method net/minecraft/client/renderer/rendertype/RenderSetup$RenderSetupBuilder.withTexture:(Ljava/lang/String;Lnet/minecraft/resources/Identifier;)Lnet/minecraft/client/renderer/rendertype/RenderSetup$RenderSetupBuilder;
      12: getstatic     #155                // Field net/minecraft/client/renderer/rendertype/RenderSetup$OutlineProperty.AFFECTS_OUTLINE:Lnet/minecraft/client/renderer/rendertype/RenderSetup$OutlineProperty;
      15: invokevirtual #159                // Method net/minecraft/client/renderer/rendertype/RenderSetup$RenderSetupBuilder.setOutline:(Lnet/minecraft/client/renderer/rendertype/RenderSetup$OutlineProperty;)Lnet/minecraft/client/renderer/rendertype/RenderSetup$RenderSetupBuilder;
      18: invokevirtual #163                // Method net/minecraft/client/renderer/rendertype/RenderSetup$RenderSetupBuilder.createRenderSetup:()Lnet/minecraft/client/renderer/rendertype/RenderSetup;
      21: astore_1
      22: ldc_w         #458                // String entity_alpha
      25: aload_1
      26: invokestatic  #169                // Method net/minecraft/client/renderer/rendertype/RenderType.create:(Ljava/lang/String;Lnet/minecraft/client/renderer/rendertype/RenderSetup;)Lnet/minecraft/client/renderer/rendertype/RenderType;
      29: areturn

  private static net.minecraft.client.renderer.rendertype.RenderType method_75955(net.minecraft.resources.Identifier);
    Code:
       0: getstatic     #461                // Field net/minecraft/client/renderer/RenderPipelines.ENTITY_SHADOW:Lcom/mojang/blaze3d/pipeline/RenderPipeline;
       3: invokestatic  #125                // Method net/minecraft/client/renderer/rendertype/RenderSetup.builder:(Lcom/mojang/blaze3d/pipeline/RenderPipeline;)Lnet/minecraft/client/renderer/rendertype/RenderSetup$RenderSetupBuilder;
       6: ldc           #127                // String Sampler0
       8: aload_0
       9: invokevirtual #131                // Method net/minecraft/client/renderer/rendertype/RenderSetup$RenderSetupBuilder.withTexture:(Ljava/lang/String;Lnet/minecraft/resources/Identifier;)Lnet/minecraft/client/renderer/rendertype/RenderSetup$RenderSetupBuilder;
      12: invokevirtual #135                // Method net/minecraft/client/renderer/rendertype/RenderSetup$RenderSetupBuilder.useLightmap:()Lnet/minecraft/client/renderer/rendertype/RenderSetup$RenderSetupBuilder;
      15: invokevirtual #138                // Method net/minecraft/client/renderer/rendertype/RenderSetup$RenderSetupBuilder.useOverlay:()Lnet/minecraft/client/renderer/rendertype/RenderSetup$RenderSetupBuilder;
      18: getstatic     #144                // Field net/minecraft/client/renderer/rendertype/LayeringTransform.VIEW_OFFSET_Z_LAYERING:Lnet/minecraft/client/renderer/rendertype/LayeringTransform;
      21: invokevirtual #148                // Method net/minecraft/client/renderer/rendertype/RenderSetup$RenderSetupBuilder.setLayeringTransform:(Lnet/minecraft/client/renderer/rendertype/LayeringTransform;)Lnet/minecraft/client/renderer/rendertype/RenderSetup$RenderSetupBuilder;
      24: invokevirtual #163                // Method net/minecraft/client/renderer/rendertype/RenderSetup$RenderSetupBuilder.createRenderSetup:()Lnet/minecraft/client/renderer/rendertype/RenderSetup;
      27: astore_1
      28: ldc_w         #463                // String entity_shadow
      31: aload_1
      32: invokestatic  #169                // Method net/minecraft/client/renderer/rendertype/RenderType.create:(Ljava/lang/String;Lnet/minecraft/client/renderer/rendertype/RenderSetup;)Lnet/minecraft/client/renderer/rendertype/RenderType;
      35: areturn

  private static net.minecraft.client.renderer.rendertype.RenderType method_75956(net.minecraft.resources.Identifier);
    Code:
       0: getstatic     #466                // Field net/minecraft/client/renderer/RenderPipelines.ENTITY_NO_OUTLINE:Lcom/mojang/blaze3d/pipeline/RenderPipeline;
       3: invokestatic  #125                // Method net/minecraft/client/renderer/rendertype/RenderSetup.builder:(Lcom/mojang/blaze3d/pipeline/RenderPipeline;)Lnet/minecraft/client/renderer/rendertype/RenderSetup$RenderSetupBuilder;
       6: ldc           #127                // String Sampler0
       8: aload_0
       9: invokevirtual #131                // Method net/minecraft/client/renderer/rendertype/RenderSetup$RenderSetupBuilder.withTexture:(Ljava/lang/String;Lnet/minecraft/resources/Identifier;)Lnet/minecraft/client/renderer/rendertype/RenderSetup$RenderSetupBuilder;
      12: invokevirtual #135                // Method net/minecraft/client/renderer/rendertype/RenderSetup$RenderSetupBuilder.useLightmap:()Lnet/minecraft/client/renderer/rendertype/RenderSetup$RenderSetupBuilder;
      15: invokevirtual #138                // Method net/minecraft/client/renderer/rendertype/RenderSetup$RenderSetupBuilder.useOverlay:()Lnet/minecraft/client/renderer/rendertype/RenderSetup$RenderSetupBuilder;
      18: invokevirtual #261                // Method net/minecraft/client/renderer/rendertype/RenderSetup$RenderSetupBuilder.sortOnUpload:()Lnet/minecraft/client/renderer/rendertype/RenderSetup$RenderSetupBuilder;
      21: invokevirtual #163                // Method net/minecraft/client/renderer/rendertype/RenderSetup$RenderSetupBuilder.createRenderSetup:()Lnet/minecraft/client/renderer/rendertype/RenderSetup;
      24: astore_1
      25: ldc_w         #468                // String entity_no_outline
      28: aload_1
      29: invokestatic  #169                // Method net/minecraft/client/renderer/rendertype/RenderType.create:(Ljava/lang/String;Lnet/minecraft/client/renderer/rendertype/RenderSetup;)Lnet/minecraft/client/renderer/rendertype/RenderType;
      32: areturn

  private static net.minecraft.client.renderer.rendertype.RenderType method_75957(net.minecraft.resources.Identifier);
    Code:
       0: getstatic     #471                // Field net/minecraft/client/renderer/RenderPipelines.ENTITY_DECAL:Lcom/mojang/blaze3d/pipeline/RenderPipeline;
       3: invokestatic  #125                // Method net/minecraft/client/renderer/rendertype/RenderSetup.builder:(Lcom/mojang/blaze3d/pipeline/RenderPipeline;)Lnet/minecraft/client/renderer/rendertype/RenderSetup$RenderSetupBuilder;
       6: ldc           #127                // String Sampler0
       8: aload_0
       9: invokevirtual #131                // Method net/minecraft/client/renderer/rendertype/RenderSetup$RenderSetupBuilder.withTexture:(Ljava/lang/String;Lnet/minecraft/resources/Identifier;)Lnet/minecraft/client/renderer/rendertype/RenderSetup$RenderSetupBuilder;
      12: invokevirtual #135                // Method net/minecraft/client/renderer/rendertype/RenderSetup$RenderSetupBuilder.useLightmap:()Lnet/minecraft/client/renderer/rendertype/RenderSetup$RenderSetupBuilder;
      15: invokevirtual #138                // Method net/minecraft/client/renderer/rendertype/RenderSetup$RenderSetupBuilder.useOverlay:()Lnet/minecraft/client/renderer/rendertype/RenderSetup$RenderSetupBuilder;
      18: invokevirtual #163                // Method net/minecraft/client/renderer/rendertype/RenderSetup$RenderSetupBuilder.createRenderSetup:()Lnet/minecraft/client/renderer/rendertype/RenderSetup;
      21: astore_1
      22: ldc_w         #473                // String entity_decal
      25: aload_1
      26: invokestatic  #169                // Method net/minecraft/client/renderer/rendertype/RenderType.create:(Ljava/lang/String;Lnet/minecraft/client/renderer/rendertype/RenderSetup;)Lnet/minecraft/client/renderer/rendertype/RenderType;
      29: areturn

  private static net.minecraft.client.renderer.rendertype.RenderType method_75968(net.minecraft.resources.Identifier, java.lang.Boolean);
    Code:
       0: aload_1
       1: invokevirtual #480                // Method java/lang/Boolean.booleanValue:()Z
       4: ifeq          13
       7: getstatic     #483                // Field net/minecraft/client/renderer/RenderPipelines.BEACON_BEAM_TRANSLUCENT:Lcom/mojang/blaze3d/pipeline/RenderPipeline;
      10: goto          16
      13: getstatic     #486                // Field net/minecraft/client/renderer/RenderPipelines.BEACON_BEAM_OPAQUE:Lcom/mojang/blaze3d/pipeline/RenderPipeline;
      16: invokestatic  #125                // Method net/minecraft/client/renderer/rendertype/RenderSetup.builder:(Lcom/mojang/blaze3d/pipeline/RenderPipeline;)Lnet/minecraft/client/renderer/rendertype/RenderSetup$RenderSetupBuilder;
      19: ldc           #127                // String Sampler0
      21: aload_0
      22: invokevirtual #131                // Method net/minecraft/client/renderer/rendertype/RenderSetup$RenderSetupBuilder.withTexture:(Ljava/lang/String;Lnet/minecraft/resources/Identifier;)Lnet/minecraft/client/renderer/rendertype/RenderSetup$RenderSetupBuilder;
      25: invokevirtual #261                // Method net/minecraft/client/renderer/rendertype/RenderSetup$RenderSetupBuilder.sortOnUpload:()Lnet/minecraft/client/renderer/rendertype/RenderSetup$RenderSetupBuilder;
      28: invokevirtual #163                // Method net/minecraft/client/renderer/rendertype/RenderSetup$RenderSetupBuilder.createRenderSetup:()Lnet/minecraft/client/renderer/rendertype/RenderSetup;
      31: astore_2
      32: ldc_w         #490                // String beacon_beam
      35: aload_2
      36: invokestatic  #169                // Method net/minecraft/client/renderer/rendertype/RenderType.create:(Ljava/lang/String;Lnet/minecraft/client/renderer/rendertype/RenderSetup;)Lnet/minecraft/client/renderer/rendertype/RenderType;
      39: areturn

  private static net.minecraft.client.renderer.rendertype.RenderType method_75958(net.minecraft.resources.Identifier);
    Code:
       0: getstatic     #494                // Field net/minecraft/client/renderer/RenderPipelines.ENTITY_SMOOTH_CUTOUT:Lcom/mojang/blaze3d/pipeline/RenderPipeline;
       3: invokestatic  #125                // Method net/minecraft/client/renderer/rendertype/RenderSetup.builder:(Lcom/mojang/blaze3d/pipeline/RenderPipeline;)Lnet/minecraft/client/renderer/rendertype/RenderSetup$RenderSetupBuilder;
       6: ldc           #127                // String Sampler0
       8: aload_0
       9: invokevirtual #131                // Method net/minecraft/client/renderer/rendertype/RenderSetup$RenderSetupBuilder.withTexture:(Ljava/lang/String;Lnet/minecraft/resources/Identifier;)Lnet/minecraft/client/renderer/rendertype/RenderSetup$RenderSetupBuilder;
      12: invokevirtual #135                // Method net/minecraft/client/renderer/rendertype/RenderSetup$RenderSetupBuilder.useLightmap:()Lnet/minecraft/client/renderer/rendertype/RenderSetup$RenderSetupBuilder;
      15: invokevirtual #138                // Method net/minecraft/client/renderer/rendertype/RenderSetup$RenderSetupBuilder.useOverlay:()Lnet/minecraft/client/renderer/rendertype/RenderSetup$RenderSetupBuilder;
      18: getstatic     #155                // Field net/minecraft/client/renderer/rendertype/RenderSetup$OutlineProperty.AFFECTS_OUTLINE:Lnet/minecraft/client/renderer/rendertype/RenderSetup$OutlineProperty;
      21: invokevirtual #159                // Method net/minecraft/client/renderer/rendertype/RenderSetup$RenderSetupBuilder.setOutline:(Lnet/minecraft/client/renderer/rendertype/RenderSetup$OutlineProperty;)Lnet/minecraft/client/renderer/rendertype/RenderSetup$RenderSetupBuilder;
      24: invokevirtual #163                // Method net/minecraft/client/renderer/rendertype/RenderSetup$RenderSetupBuilder.createRenderSetup:()Lnet/minecraft/client/renderer/rendertype/RenderSetup;
      27: astore_1
      28: ldc_w         #496                // String entity_smooth_cutout
      31: aload_1
      32: invokestatic  #169                // Method net/minecraft/client/renderer/rendertype/RenderType.create:(Ljava/lang/String;Lnet/minecraft/client/renderer/rendertype/RenderSetup;)Lnet/minecraft/client/renderer/rendertype/RenderType;
      35: areturn

  private static net.minecraft.client.renderer.rendertype.RenderType method_75975(net.minecraft.resources.Identifier, java.lang.Boolean);
    Code:
       0: getstatic     #499                // Field net/minecraft/client/renderer/RenderPipelines.ENTITY_TRANSLUCENT_EMISSIVE:Lcom/mojang/blaze3d/pipeline/RenderPipeline;
       3: invokestatic  #125                // Method net/minecraft/client/renderer/rendertype/RenderSetup.builder:(Lcom/mojang/blaze3d/pipeline/RenderPipeline;)Lnet/minecraft/client/renderer/rendertype/RenderSetup$RenderSetupBuilder;
       6: ldc           #127                // String Sampler0
       8: aload_0
       9: invokevirtual #131                // Method net/minecraft/client/renderer/rendertype/RenderSetup$RenderSetupBuilder.withTexture:(Ljava/lang/String;Lnet/minecraft/resources/Identifier;)Lnet/minecraft/client/renderer/rendertype/RenderSetup$RenderSetupBuilder;
      12: invokevirtual #138                // Method net/minecraft/client/renderer/rendertype/RenderSetup$RenderSetupBuilder.useOverlay:()Lnet/minecraft/client/renderer/rendertype/RenderSetup$RenderSetupBuilder;
      15: invokevirtual #151                // Method net/minecraft/client/renderer/rendertype/RenderSetup$RenderSetupBuilder.affectsCrumbling:()Lnet/minecraft/client/renderer/rendertype/RenderSetup$RenderSetupBuilder;
      18: invokevirtual #261                // Method net/minecraft/client/renderer/rendertype/RenderSetup$RenderSetupBuilder.sortOnUpload:()Lnet/minecraft/client/renderer/rendertype/RenderSetup$RenderSetupBuilder;
      21: aload_1
      22: invokevirtual #480                // Method java/lang/Boolean.booleanValue:()Z
      25: ifeq          34
      28: getstatic     #155                // Field net/minecraft/client/renderer/rendertype/RenderSetup$OutlineProperty.AFFECTS_OUTLINE:Lnet/minecraft/client/renderer/rendertype/RenderSetup$OutlineProperty;
      31: goto          37
      34: getstatic     #502                // Field net/minecraft/client/renderer/rendertype/RenderSetup$OutlineProperty.NONE:Lnet/minecraft/client/renderer/rendertype/RenderSetup$OutlineProperty;
      37: invokevirtual #159                // Method net/minecraft/client/renderer/rendertype/RenderSetup$RenderSetupBuilder.setOutline:(Lnet/minecraft/client/renderer/rendertype/RenderSetup$OutlineProperty;)Lnet/minecraft/client/renderer/rendertype/RenderSetup$RenderSetupBuilder;
      40: invokevirtual #163                // Method net/minecraft/client/renderer/rendertype/RenderSetup$RenderSetupBuilder.createRenderSetup:()Lnet/minecraft/client/renderer/rendertype/RenderSetup;
      43: astore_2
      44: ldc_w         #504                // String entity_translucent_emissive
      47: aload_2
      48: invokestatic  #169                // Method net/minecraft/client/renderer/rendertype/RenderType.create:(Ljava/lang/String;Lnet/minecraft/client/renderer/rendertype/RenderSetup;)Lnet/minecraft/client/renderer/rendertype/RenderType;
      51: areturn

  private static net.minecraft.client.renderer.rendertype.RenderType method_75979(net.minecraft.resources.Identifier, java.lang.Boolean);
    Code:
       0: getstatic     #507                // Field net/minecraft/client/renderer/RenderPipelines.ENTITY_TRANSLUCENT:Lcom/mojang/blaze3d/pipeline/RenderPipeline;
       3: invokestatic  #125                // Method net/minecraft/client/renderer/rendertype/RenderSetup.builder:(Lcom/mojang/blaze3d/pipeline/RenderPipeline;)Lnet/minecraft/client/renderer/rendertype/RenderSetup$RenderSetupBuilder;
       6: ldc           #127                // String Sampler0
       8: aload_0
       9: invokevirtual #131                // Method net/minecraft/client/renderer/rendertype/RenderSetup$RenderSetupBuilder.withTexture:(Ljava/lang/String;Lnet/minecraft/resources/Identifier;)Lnet/minecraft/client/renderer/rendertype/RenderSetup$RenderSetupBuilder;
      12: invokevirtual #135                // Method net/minecraft/client/renderer/rendertype/RenderSetup$RenderSetupBuilder.useLightmap:()Lnet/minecraft/client/renderer/rendertype/RenderSetup$RenderSetupBuilder;
      15: invokevirtual #138                // Method net/minecraft/client/renderer/rendertype/RenderSetup$RenderSetupBuilder.useOverlay:()Lnet/minecraft/client/renderer/rendertype/RenderSetup$RenderSetupBuilder;
      18: invokevirtual #151                // Method net/minecraft/client/renderer/rendertype/RenderSetup$RenderSetupBuilder.affectsCrumbling:()Lnet/minecraft/client/renderer/rendertype/RenderSetup$RenderSetupBuilder;
      21: invokevirtual #261                // Method net/minecraft/client/renderer/rendertype/RenderSetup$RenderSetupBuilder.sortOnUpload:()Lnet/minecraft/client/renderer/rendertype/RenderSetup$RenderSetupBuilder;
      24: aload_1
      25: invokevirtual #480                // Method java/lang/Boolean.booleanValue:()Z
      28: ifeq          37
      31: getstatic     #155                // Field net/minecraft/client/renderer/rendertype/RenderSetup$OutlineProperty.AFFECTS_OUTLINE:Lnet/minecraft/client/renderer/rendertype/RenderSetup$OutlineProperty;
      34: goto          40
      37: getstatic     #502                // Field net/minecraft/client/renderer/rendertype/RenderSetup$OutlineProperty.NONE:Lnet/minecraft/client/renderer/rendertype/RenderSetup$OutlineProperty;
      40: invokevirtual #159                // Method net/minecraft/client/renderer/rendertype/RenderSetup$RenderSetupBuilder.setOutline:(Lnet/minecraft/client/renderer/rendertype/RenderSetup$OutlineProperty;)Lnet/minecraft/client/renderer/rendertype/RenderSetup$RenderSetupBuilder;
      43: invokevirtual #163                // Method net/minecraft/client/renderer/rendertype/RenderSetup$RenderSetupBuilder.createRenderSetup:()Lnet/minecraft/client/renderer/rendertype/RenderSetup;
      46: astore_2
      47: ldc_w         #509                // String entity_translucent
      50: aload_2
      51: invokestatic  #169                // Method net/minecraft/client/renderer/rendertype/RenderType.create:(Ljava/lang/String;Lnet/minecraft/client/renderer/rendertype/RenderSetup;)Lnet/minecraft/client/renderer/rendertype/RenderType;
      54: areturn

  private static net.minecraft.client.renderer.rendertype.RenderType method_75959(net.minecraft.resources.Identifier);
    Code:
       0: getstatic     #512                // Field net/minecraft/client/renderer/RenderPipelines.ITEM_ENTITY_TRANSLUCENT_CULL:Lcom/mojang/blaze3d/pipeline/RenderPipeline;
       3: invokestatic  #125                // Method net/minecraft/client/renderer/rendertype/RenderSetup.builder:(Lcom/mojang/blaze3d/pipeline/RenderPipeline;)Lnet/minecraft/client/renderer/rendertype/RenderSetup$RenderSetupBuilder;
       6: ldc           #127                // String Sampler0
       8: aload_0
       9: invokevirtual #131                // Method net/minecraft/client/renderer/rendertype/RenderSetup$RenderSetupBuilder.withTexture:(Ljava/lang/String;Lnet/minecraft/resources/Identifier;)Lnet/minecraft/client/renderer/rendertype/RenderSetup$RenderSetupBuilder;
      12: getstatic     #515                // Field net/minecraft/client/renderer/rendertype/OutputTarget.ITEM_ENTITY_TARGET:Lnet/minecraft/client/renderer/rendertype/OutputTarget;
      15: invokevirtual #413                // Method net/minecraft/client/renderer/rendertype/RenderSetup$RenderSetupBuilder.setOutputTarget:(Lnet/minecraft/client/renderer/rendertype/OutputTarget;)Lnet/minecraft/client/renderer/rendertype/RenderSetup$RenderSetupBuilder;
      18: invokevirtual #135                // Method net/minecraft/client/renderer/rendertype/RenderSetup$RenderSetupBuilder.useLightmap:()Lnet/minecraft/client/renderer/rendertype/RenderSetup$RenderSetupBuilder;
      21: invokevirtual #138                // Method net/minecraft/client/renderer/rendertype/RenderSetup$RenderSetupBuilder.useOverlay:()Lnet/minecraft/client/renderer/rendertype/RenderSetup$RenderSetupBuilder;
      24: invokevirtual #151                // Method net/minecraft/client/renderer/rendertype/RenderSetup$RenderSetupBuilder.affectsCrumbling:()Lnet/minecraft/client/renderer/rendertype/RenderSetup$RenderSetupBuilder;
      27: invokevirtual #261                // Method net/minecraft/client/renderer/rendertype/RenderSetup$RenderSetupBuilder.sortOnUpload:()Lnet/minecraft/client/renderer/rendertype/RenderSetup$RenderSetupBuilder;
      30: getstatic     #155                // Field net/minecraft/client/renderer/rendertype/RenderSetup$OutlineProperty.AFFECTS_OUTLINE:Lnet/minecraft/client/renderer/rendertype/RenderSetup$OutlineProperty;
      33: invokevirtual #159                // Method net/minecraft/client/renderer/rendertype/RenderSetup$RenderSetupBuilder.setOutline:(Lnet/minecraft/client/renderer/rendertype/RenderSetup$OutlineProperty;)Lnet/minecraft/client/renderer/rendertype/RenderSetup$RenderSetupBuilder;
      36: invokevirtual #163                // Method net/minecraft/client/renderer/rendertype/RenderSetup$RenderSetupBuilder.createRenderSetup:()Lnet/minecraft/client/renderer/rendertype/RenderSetup;
      39: astore_1
      40: ldc_w         #517                // String item_entity_translucent_cull
      43: aload_1
      44: invokestatic  #169                // Method net/minecraft/client/renderer/rendertype/RenderType.create:(Ljava/lang/String;Lnet/minecraft/client/renderer/rendertype/RenderSetup;)Lnet/minecraft/client/renderer/rendertype/RenderType;
      47: areturn

  private static net.minecraft.client.renderer.rendertype.RenderType method_75983(net.minecraft.resources.Identifier, java.lang.Boolean);
    Code:
       0: getstatic     #520                // Field net/minecraft/client/renderer/RenderPipelines.ENTITY_CUTOUT_NO_CULL_Z_OFFSET:Lcom/mojang/blaze3d/pipeline/RenderPipeline;
       3: invokestatic  #125                // Method net/minecraft/client/renderer/rendertype/RenderSetup.builder:(Lcom/mojang/blaze3d/pipeline/RenderPipeline;)Lnet/minecraft/client/renderer/rendertype/RenderSetup$RenderSetupBuilder;
       6: ldc           #127                // String Sampler0
       8: aload_0
       9: invokevirtual #131                // Method net/minecraft/client/renderer/rendertype/RenderSetup$RenderSetupBuilder.withTexture:(Ljava/lang/String;Lnet/minecraft/resources/Identifier;)Lnet/minecraft/client/renderer/rendertype/RenderSetup$RenderSetupBuilder;
      12: invokevirtual #135                // Method net/minecraft/client/renderer/rendertype/RenderSetup$RenderSetupBuilder.useLightmap:()Lnet/minecraft/client/renderer/rendertype/RenderSetup$RenderSetupBuilder;
      15: invokevirtual #138                // Method net/minecraft/client/renderer/rendertype/RenderSetup$RenderSetupBuilder.useOverlay:()Lnet/minecraft/client/renderer/rendertype/RenderSetup$RenderSetupBuilder;
      18: getstatic     #144                // Field net/minecraft/client/renderer/rendertype/LayeringTransform.VIEW_OFFSET_Z_LAYERING:Lnet/minecraft/client/renderer/rendertype/LayeringTransform;
      21: invokevirtual #148                // Method net/minecraft/client/renderer/rendertype/RenderSetup$RenderSetupBuilder.setLayeringTransform:(Lnet/minecraft/client/renderer/rendertype/LayeringTransform;)Lnet/minecraft/client/renderer/rendertype/RenderSetup$RenderSetupBuilder;
      24: invokevirtual #151                // Method net/minecraft/client/renderer/rendertype/RenderSetup$RenderSetupBuilder.affectsCrumbling:()Lnet/minecraft/client/renderer/rendertype/RenderSetup$RenderSetupBuilder;
      27: aload_1
      28: invokevirtual #480                // Method java/lang/Boolean.booleanValue:()Z
      31: ifeq          40
      34: getstatic     #155                // Field net/minecraft/client/renderer/rendertype/RenderSetup$OutlineProperty.AFFECTS_OUTLINE:Lnet/minecraft/client/renderer/rendertype/RenderSetup$OutlineProperty;
      37: goto          43
      40: getstatic     #502                // Field net/minecraft/client/renderer/rendertype/RenderSetup$OutlineProperty.NONE:Lnet/minecraft/client/renderer/rendertype/RenderSetup$OutlineProperty;
      43: invokevirtual #159                // Method net/minecraft/client/renderer/rendertype/RenderSetup$RenderSetupBuilder.setOutline:(Lnet/minecraft/client/renderer/rendertype/RenderSetup$OutlineProperty;)Lnet/minecraft/client/renderer/rendertype/RenderSetup$RenderSetupBuilder;
      46: invokevirtual #163                // Method net/minecraft/client/renderer/rendertype/RenderSetup$RenderSetupBuilder.createRenderSetup:()Lnet/minecraft/client/renderer/rendertype/RenderSetup;
      49: astore_2
      50: ldc_w         #522                // String entity_cutout_no_cull_z_offset
      53: aload_2
      54: invokestatic  #169                // Method net/minecraft/client/renderer/rendertype/RenderType.create:(Ljava/lang/String;Lnet/minecraft/client/renderer/rendertype/RenderSetup;)Lnet/minecraft/client/renderer/rendertype/RenderType;
      57: areturn

  private static net.minecraft.client.renderer.rendertype.RenderType method_75987(net.minecraft.resources.Identifier, java.lang.Boolean);
    Code:
       0: getstatic     #525                // Field net/minecraft/client/renderer/RenderPipelines.ENTITY_CUTOUT_NO_CULL:Lcom/mojang/blaze3d/pipeline/RenderPipeline;
       3: invokestatic  #125                // Method net/minecraft/client/renderer/rendertype/RenderSetup.builder:(Lcom/mojang/blaze3d/pipeline/RenderPipeline;)Lnet/minecraft/client/renderer/rendertype/RenderSetup$RenderSetupBuilder;
       6: ldc           #127                // String Sampler0
       8: aload_0
       9: invokevirtual #131                // Method net/minecraft/client/renderer/rendertype/RenderSetup$RenderSetupBuilder.withTexture:(Ljava/lang/String;Lnet/minecraft/resources/Identifier;)Lnet/minecraft/client/renderer/rendertype/RenderSetup$RenderSetupBuilder;
      12: invokevirtual #135                // Method net/minecraft/client/renderer/rendertype/RenderSetup$RenderSetupBuilder.useLightmap:()Lnet/minecraft/client/renderer/rendertype/RenderSetup$RenderSetupBuilder;
      15: invokevirtual #138                // Method net/minecraft/client/renderer/rendertype/RenderSetup$RenderSetupBuilder.useOverlay:()Lnet/minecraft/client/renderer/rendertype/RenderSetup$RenderSetupBuilder;
      18: invokevirtual #151                // Method net/minecraft/client/renderer/rendertype/RenderSetup$RenderSetupBuilder.affectsCrumbling:()Lnet/minecraft/client/renderer/rendertype/RenderSetup$RenderSetupBuilder;
      21: aload_1
      22: invokevirtual #480                // Method java/lang/Boolean.booleanValue:()Z
      25: ifeq          34
      28: getstatic     #155                // Field net/minecraft/client/renderer/rendertype/RenderSetup$OutlineProperty.AFFECTS_OUTLINE:Lnet/minecraft/client/renderer/rendertype/RenderSetup$OutlineProperty;
      31: goto          37
      34: getstatic     #502                // Field net/minecraft/client/renderer/rendertype/RenderSetup$OutlineProperty.NONE:Lnet/minecraft/client/renderer/rendertype/RenderSetup$OutlineProperty;
      37: invokevirtual #159                // Method net/minecraft/client/renderer/rendertype/RenderSetup$RenderSetupBuilder.setOutline:(Lnet/minecraft/client/renderer/rendertype/RenderSetup$OutlineProperty;)Lnet/minecraft/client/renderer/rendertype/RenderSetup$RenderSetupBuilder;
      40: invokevirtual #163                // Method net/minecraft/client/renderer/rendertype/RenderSetup$RenderSetupBuilder.createRenderSetup:()Lnet/minecraft/client/renderer/rendertype/RenderSetup;
      43: astore_2
      44: ldc_w         #527                // String entity_cutout_no_cull
      47: aload_2
      48: invokestatic  #169                // Method net/minecraft/client/renderer/rendertype/RenderType.create:(Ljava/lang/String;Lnet/minecraft/client/renderer/rendertype/RenderSetup;)Lnet/minecraft/client/renderer/rendertype/RenderType;
      51: areturn

  private static net.minecraft.client.renderer.rendertype.RenderType method_75960(net.minecraft.resources.Identifier);
    Code:
       0: getstatic     #530                // Field net/minecraft/client/renderer/RenderPipelines.ENTITY_CUTOUT:Lcom/mojang/blaze3d/pipeline/RenderPipeline;
       3: invokestatic  #125                // Method net/minecraft/client/renderer/rendertype/RenderSetup.builder:(Lcom/mojang/blaze3d/pipeline/RenderPipeline;)Lnet/minecraft/client/renderer/rendertype/RenderSetup$RenderSetupBuilder;
       6: ldc           #127                // String Sampler0
       8: aload_0
       9: invokevirtual #131                // Method net/minecraft/client/renderer/rendertype/RenderSetup$RenderSetupBuilder.withTexture:(Ljava/lang/String;Lnet/minecraft/resources/Identifier;)Lnet/minecraft/client/renderer/rendertype/RenderSetup$RenderSetupBuilder;
      12: invokevirtual #135                // Method net/minecraft/client/renderer/rendertype/RenderSetup$RenderSetupBuilder.useLightmap:()Lnet/minecraft/client/renderer/rendertype/RenderSetup$RenderSetupBuilder;
      15: invokevirtual #138                // Method net/minecraft/client/renderer/rendertype/RenderSetup$RenderSetupBuilder.useOverlay:()Lnet/minecraft/client/renderer/rendertype/RenderSetup$RenderSetupBuilder;
      18: invokevirtual #151                // Method net/minecraft/client/renderer/rendertype/RenderSetup$RenderSetupBuilder.affectsCrumbling:()Lnet/minecraft/client/renderer/rendertype/RenderSetup$RenderSetupBuilder;
      21: getstatic     #155                // Field net/minecraft/client/renderer/rendertype/RenderSetup$OutlineProperty.AFFECTS_OUTLINE:Lnet/minecraft/client/renderer/rendertype/RenderSetup$OutlineProperty;
      24: invokevirtual #159                // Method net/minecraft/client/renderer/rendertype/RenderSetup$RenderSetupBuilder.setOutline:(Lnet/minecraft/client/renderer/rendertype/RenderSetup$OutlineProperty;)Lnet/minecraft/client/renderer/rendertype/RenderSetup$RenderSetupBuilder;
      27: invokevirtual #163                // Method net/minecraft/client/renderer/rendertype/RenderSetup$RenderSetupBuilder.createRenderSetup:()Lnet/minecraft/client/renderer/rendertype/RenderSetup;
      30: astore_1
      31: ldc_w         #532                // String entity_cutout
      34: aload_1
      35: invokestatic  #169                // Method net/minecraft/client/renderer/rendertype/RenderType.create:(Ljava/lang/String;Lnet/minecraft/client/renderer/rendertype/RenderSetup;)Lnet/minecraft/client/renderer/rendertype/RenderType;
      38: areturn

  private static net.minecraft.client.renderer.rendertype.RenderType method_75961(net.minecraft.resources.Identifier);
    Code:
       0: getstatic     #535                // Field net/minecraft/client/renderer/RenderPipelines.ENTITY_SOLID_Z_OFFSET_FORWARD:Lcom/mojang/blaze3d/pipeline/RenderPipeline;
       3: invokestatic  #125                // Method net/minecraft/client/renderer/rendertype/RenderSetup.builder:(Lcom/mojang/blaze3d/pipeline/RenderPipeline;)Lnet/minecraft/client/renderer/rendertype/RenderSetup$RenderSetupBuilder;
       6: ldc           #127                // String Sampler0
       8: aload_0
       9: invokevirtual #131                // Method net/minecraft/client/renderer/rendertype/RenderSetup$RenderSetupBuilder.withTexture:(Ljava/lang/String;Lnet/minecraft/resources/Identifier;)Lnet/minecraft/client/renderer/rendertype/RenderSetup$RenderSetupBuilder;
      12: invokevirtual #135                // Method net/minecraft/client/renderer/rendertype/RenderSetup$RenderSetupBuilder.useLightmap:()Lnet/minecraft/client/renderer/rendertype/RenderSetup$RenderSetupBuilder;
      15: invokevirtual #138                // Method net/minecraft/client/renderer/rendertype/RenderSetup$RenderSetupBuilder.useOverlay:()Lnet/minecraft/client/renderer/rendertype/RenderSetup$RenderSetupBuilder;
      18: getstatic     #538                // Field net/minecraft/client/renderer/rendertype/LayeringTransform.VIEW_OFFSET_Z_LAYERING_FORWARD:Lnet/minecraft/client/renderer/rendertype/LayeringTransform;
      21: invokevirtual #148                // Method net/minecraft/client/renderer/rendertype/RenderSetup$RenderSetupBuilder.setLayeringTransform:(Lnet/minecraft/client/renderer/rendertype/LayeringTransform;)Lnet/minecraft/client/renderer/rendertype/RenderSetup$RenderSetupBuilder;
      24: invokevirtual #151                // Method net/minecraft/client/renderer/rendertype/RenderSetup$RenderSetupBuilder.affectsCrumbling:()Lnet/minecraft/client/renderer/rendertype/RenderSetup$RenderSetupBuilder;
      27: getstatic     #155                // Field net/minecraft/client/renderer/rendertype/RenderSetup$OutlineProperty.AFFECTS_OUTLINE:Lnet/minecraft/client/renderer/rendertype/RenderSetup$OutlineProperty;
      30: invokevirtual #159                // Method net/minecraft/client/renderer/rendertype/RenderSetup$RenderSetupBuilder.setOutline:(Lnet/minecraft/client/renderer/rendertype/RenderSetup$OutlineProperty;)Lnet/minecraft/client/renderer/rendertype/RenderSetup$RenderSetupBuilder;
      33: invokevirtual #163                // Method net/minecraft/client/renderer/rendertype/RenderSetup$RenderSetupBuilder.createRenderSetup:()Lnet/minecraft/client/renderer/rendertype/RenderSetup;
      36: astore_1
      37: ldc_w         #540                // String entity_solid_z_offset_forward
      40: aload_1
      41: invokestatic  #169                // Method net/minecraft/client/renderer/rendertype/RenderType.create:(Ljava/lang/String;Lnet/minecraft/client/renderer/rendertype/RenderSetup;)Lnet/minecraft/client/renderer/rendertype/RenderType;
      44: areturn

  private static net.minecraft.client.renderer.rendertype.RenderType method_75962(net.minecraft.resources.Identifier);
    Code:
       0: getstatic     #543                // Field net/minecraft/client/renderer/RenderPipelines.ENTITY_SOLID:Lcom/mojang/blaze3d/pipeline/RenderPipeline;
       3: invokestatic  #125                // Method net/minecraft/client/renderer/rendertype/RenderSetup.builder:(Lcom/mojang/blaze3d/pipeline/RenderPipeline;)Lnet/minecraft/client/renderer/rendertype/RenderSetup$RenderSetupBuilder;
       6: ldc           #127                // String Sampler0
       8: aload_0
       9: invokevirtual #131                // Method net/minecraft/client/renderer/rendertype/RenderSetup$RenderSetupBuilder.withTexture:(Ljava/lang/String;Lnet/minecraft/resources/Identifier;)Lnet/minecraft/client/renderer/rendertype/RenderSetup$RenderSetupBuilder;
      12: invokevirtual #135                // Method net/minecraft/client/renderer/rendertype/RenderSetup$RenderSetupBuilder.useLightmap:()Lnet/minecraft/client/renderer/rendertype/RenderSetup$RenderSetupBuilder;
      15: invokevirtual #138                // Method net/minecraft/client/renderer/rendertype/RenderSetup$RenderSetupBuilder.useOverlay:()Lnet/minecraft/client/renderer/rendertype/RenderSetup$RenderSetupBuilder;
      18: invokevirtual #151                // Method net/minecraft/client/renderer/rendertype/RenderSetup$RenderSetupBuilder.affectsCrumbling:()Lnet/minecraft/client/renderer/rendertype/RenderSetup$RenderSetupBuilder;
      21: getstatic     #155                // Field net/minecraft/client/renderer/rendertype/RenderSetup$OutlineProperty.AFFECTS_OUTLINE:Lnet/minecraft/client/renderer/rendertype/RenderSetup$OutlineProperty;
      24: invokevirtual #159                // Method net/minecraft/client/renderer/rendertype/RenderSetup$RenderSetupBuilder.setOutline:(Lnet/minecraft/client/renderer/rendertype/RenderSetup$OutlineProperty;)Lnet/minecraft/client/renderer/rendertype/RenderSetup$RenderSetupBuilder;
      27: invokevirtual #163                // Method net/minecraft/client/renderer/rendertype/RenderSetup$RenderSetupBuilder.createRenderSetup:()Lnet/minecraft/client/renderer/rendertype/RenderSetup;
      30: astore_1
      31: ldc_w         #545                // String entity_solid
      34: aload_1
      35: invokestatic  #169                // Method net/minecraft/client/renderer/rendertype/RenderType.create:(Ljava/lang/String;Lnet/minecraft/client/renderer/rendertype/RenderSetup;)Lnet/minecraft/client/renderer/rendertype/RenderType;
      38: areturn

  private static net.minecraft.client.renderer.rendertype.RenderType method_75963(net.minecraft.resources.Identifier);
    Code:
       0: getstatic     #548                // Field net/minecraft/client/renderer/RenderPipelines.ARMOR_TRANSLUCENT:Lcom/mojang/blaze3d/pipeline/RenderPipeline;
       3: invokestatic  #125                // Method net/minecraft/client/renderer/rendertype/RenderSetup.builder:(Lcom/mojang/blaze3d/pipeline/RenderPipeline;)Lnet/minecraft/client/renderer/rendertype/RenderSetup$RenderSetupBuilder;
       6: ldc           #127                // String Sampler0
       8: aload_0
       9: invokevirtual #131                // Method net/minecraft/client/renderer/rendertype/RenderSetup$RenderSetupBuilder.withTexture:(Ljava/lang/String;Lnet/minecraft/resources/Identifier;)Lnet/minecraft/client/renderer/rendertype/RenderSetup$RenderSetupBuilder;
      12: invokevirtual #135                // Method net/minecraft/client/renderer/rendertype/RenderSetup$RenderSetupBuilder.useLightmap:()Lnet/minecraft/client/renderer/rendertype/RenderSetup$RenderSetupBuilder;
      15: invokevirtual #138                // Method net/minecraft/client/renderer/rendertype/RenderSetup$RenderSetupBuilder.useOverlay:()Lnet/minecraft/client/renderer/rendertype/RenderSetup$RenderSetupBuilder;
      18: getstatic     #144                // Field net/minecraft/client/renderer/rendertype/LayeringTransform.VIEW_OFFSET_Z_LAYERING:Lnet/minecraft/client/renderer/rendertype/LayeringTransform;
      21: invokevirtual #148                // Method net/minecraft/client/renderer/rendertype/RenderSetup$RenderSetupBuilder.setLayeringTransform:(Lnet/minecraft/client/renderer/rendertype/LayeringTransform;)Lnet/minecraft/client/renderer/rendertype/RenderSetup$RenderSetupBuilder;
      24: invokevirtual #151                // Method net/minecraft/client/renderer/rendertype/RenderSetup$RenderSetupBuilder.affectsCrumbling:()Lnet/minecraft/client/renderer/rendertype/RenderSetup$RenderSetupBuilder;
      27: invokevirtual #261                // Method net/minecraft/client/renderer/rendertype/RenderSetup$RenderSetupBuilder.sortOnUpload:()Lnet/minecraft/client/renderer/rendertype/RenderSetup$RenderSetupBuilder;
      30: getstatic     #155                // Field net/minecraft/client/renderer/rendertype/RenderSetup$OutlineProperty.AFFECTS_OUTLINE:Lnet/minecraft/client/renderer/rendertype/RenderSetup$OutlineProperty;
      33: invokevirtual #159                // Method net/minecraft/client/renderer/rendertype/RenderSetup$RenderSetupBuilder.setOutline:(Lnet/minecraft/client/renderer/rendertype/RenderSetup$OutlineProperty;)Lnet/minecraft/client/renderer/rendertype/RenderSetup$RenderSetupBuilder;
      36: invokevirtual #163                // Method net/minecraft/client/renderer/rendertype/RenderSetup$RenderSetupBuilder.createRenderSetup:()Lnet/minecraft/client/renderer/rendertype/RenderSetup;
      39: astore_1
      40: ldc_w         #550                // String armor_translucent
      43: aload_1
      44: invokestatic  #169                // Method net/minecraft/client/renderer/rendertype/RenderType.create:(Ljava/lang/String;Lnet/minecraft/client/renderer/rendertype/RenderSetup;)Lnet/minecraft/client/renderer/rendertype/RenderType;
      47: areturn

  private static net.minecraft.client.renderer.rendertype.RenderType method_75964(net.minecraft.resources.Identifier);
    Code:
       0: getstatic     #553                // Field net/minecraft/client/renderer/RenderPipelines.ARMOR_CUTOUT_NO_CULL:Lcom/mojang/blaze3d/pipeline/RenderPipeline;
       3: invokestatic  #125                // Method net/minecraft/client/renderer/rendertype/RenderSetup.builder:(Lcom/mojang/blaze3d/pipeline/RenderPipeline;)Lnet/minecraft/client/renderer/rendertype/RenderSetup$RenderSetupBuilder;
       6: ldc           #127                // String Sampler0
       8: aload_0
       9: invokevirtual #131                // Method net/minecraft/client/renderer/rendertype/RenderSetup$RenderSetupBuilder.withTexture:(Ljava/lang/String;Lnet/minecraft/resources/Identifier;)Lnet/minecraft/client/renderer/rendertype/RenderSetup$RenderSetupBuilder;
      12: invokevirtual #135                // Method net/minecraft/client/renderer/rendertype/RenderSetup$RenderSetupBuilder.useLightmap:()Lnet/minecraft/client/renderer/rendertype/RenderSetup$RenderSetupBuilder;
      15: invokevirtual #138                // Method net/minecraft/client/renderer/rendertype/RenderSetup$RenderSetupBuilder.useOverlay:()Lnet/minecraft/client/renderer/rendertype/RenderSetup$RenderSetupBuilder;
      18: getstatic     #144                // Field net/minecraft/client/renderer/rendertype/LayeringTransform.VIEW_OFFSET_Z_LAYERING:Lnet/minecraft/client/renderer/rendertype/LayeringTransform;
      21: invokevirtual #148                // Method net/minecraft/client/renderer/rendertype/RenderSetup$RenderSetupBuilder.setLayeringTransform:(Lnet/minecraft/client/renderer/rendertype/LayeringTransform;)Lnet/minecraft/client/renderer/rendertype/RenderSetup$RenderSetupBuilder;
      24: invokevirtual #151                // Method net/minecraft/client/renderer/rendertype/RenderSetup$RenderSetupBuilder.affectsCrumbling:()Lnet/minecraft/client/renderer/rendertype/RenderSetup$RenderSetupBuilder;
      27: getstatic     #155                // Field net/minecraft/client/renderer/rendertype/RenderSetup$OutlineProperty.AFFECTS_OUTLINE:Lnet/minecraft/client/renderer/rendertype/RenderSetup$OutlineProperty;
      30: invokevirtual #159                // Method net/minecraft/client/renderer/rendertype/RenderSetup$RenderSetupBuilder.setOutline:(Lnet/minecraft/client/renderer/rendertype/RenderSetup$OutlineProperty;)Lnet/minecraft/client/renderer/rendertype/RenderSetup$RenderSetupBuilder;
      33: invokevirtual #163                // Method net/minecraft/client/renderer/rendertype/RenderSetup$RenderSetupBuilder.createRenderSetup:()Lnet/minecraft/client/renderer/rendertype/RenderSetup;
      36: astore_1
      37: ldc_w         #555                // String armor_cutout_no_cull
      40: aload_1
      41: invokestatic  #169                // Method net/minecraft/client/renderer/rendertype/RenderType.create:(Ljava/lang/String;Lnet/minecraft/client/renderer/rendertype/RenderSetup;)Lnet/minecraft/client/renderer/rendertype/RenderType;
      44: areturn

  private static com.mojang.blaze3d.textures.GpuSampler method_76563();
    Code:
       0: invokestatic  #563                // Method com/mojang/blaze3d/systems/RenderSystem.getSamplerCache:()Lcom/mojang/blaze3d/systems/SamplerCache;
       3: getstatic     #569                // Field com/mojang/blaze3d/textures/AddressMode.CLAMP_TO_EDGE:Lcom/mojang/blaze3d/textures/AddressMode;
       6: getstatic     #569                // Field com/mojang/blaze3d/textures/AddressMode.CLAMP_TO_EDGE:Lcom/mojang/blaze3d/textures/AddressMode;
       9: getstatic     #575                // Field com/mojang/blaze3d/textures/FilterMode.LINEAR:Lcom/mojang/blaze3d/textures/FilterMode;
      12: getstatic     #578                // Field com/mojang/blaze3d/textures/FilterMode.NEAREST:Lcom/mojang/blaze3d/textures/FilterMode;
      15: iconst_1
      16: invokevirtual #584                // Method com/mojang/blaze3d/systems/SamplerCache.getSampler:(Lcom/mojang/blaze3d/textures/AddressMode;Lcom/mojang/blaze3d/textures/AddressMode;Lcom/mojang/blaze3d/textures/FilterMode;Lcom/mojang/blaze3d/textures/FilterMode;Z)Lcom/mojang/blaze3d/textures/GpuSampler;
      19: areturn

  private static net.minecraft.client.renderer.rendertype.RenderType method_75991(net.minecraft.resources.Identifier, java.lang.Boolean);
    Code:
       0: ldc_w         #586                // String outline
       3: aload_1
       4: invokevirtual #480                // Method java/lang/Boolean.booleanValue:()Z
       7: ifeq          16
      10: getstatic     #589                // Field net/minecraft/client/renderer/RenderPipelines.OUTLINE_CULL:Lcom/mojang/blaze3d/pipeline/RenderPipeline;
      13: goto          19
      16: getstatic     #596                // Field net/minecraft/client/renderer/RenderPipelines.OUTLINE_NO_CULL:Lcom/mojang/blaze3d/pipeline/RenderPipeline;
      19: invokestatic  #125                // Method net/minecraft/client/renderer/rendertype/RenderSetup.builder:(Lcom/mojang/blaze3d/pipeline/RenderPipeline;)Lnet/minecraft/client/renderer/rendertype/RenderSetup$RenderSetupBuilder;
      22: ldc           #127                // String Sampler0
      24: aload_0
      25: invokevirtual #131                // Method net/minecraft/client/renderer/rendertype/RenderSetup$RenderSetupBuilder.withTexture:(Ljava/lang/String;Lnet/minecraft/resources/Identifier;)Lnet/minecraft/client/renderer/rendertype/RenderSetup$RenderSetupBuilder;
      28: getstatic     #599                // Field net/minecraft/client/renderer/rendertype/OutputTarget.OUTLINE_TARGET:Lnet/minecraft/client/renderer/rendertype/OutputTarget;
      31: invokevirtual #413                // Method net/minecraft/client/renderer/rendertype/RenderSetup$RenderSetupBuilder.setOutputTarget:(Lnet/minecraft/client/renderer/rendertype/OutputTarget;)Lnet/minecraft/client/renderer/rendertype/RenderSetup$RenderSetupBuilder;
      34: getstatic     #602                // Field net/minecraft/client/renderer/rendertype/RenderSetup$OutlineProperty.IS_OUTLINE:Lnet/minecraft/client/renderer/rendertype/RenderSetup$OutlineProperty;
      37: invokevirtual #159                // Method net/minecraft/client/renderer/rendertype/RenderSetup$RenderSetupBuilder.setOutline:(Lnet/minecraft/client/renderer/rendertype/RenderSetup$OutlineProperty;)Lnet/minecraft/client/renderer/rendertype/RenderSetup$RenderSetupBuilder;
      40: invokevirtual #163                // Method net/minecraft/client/renderer/rendertype/RenderSetup$RenderSetupBuilder.createRenderSetup:()Lnet/minecraft/client/renderer/rendertype/RenderSetup;
      43: invokestatic  #169                // Method net/minecraft/client/renderer/rendertype/RenderType.create:(Ljava/lang/String;Lnet/minecraft/client/renderer/rendertype/RenderSetup;)Lnet/minecraft/client/renderer/rendertype/RenderType;
      46: areturn

  static {};
    Code:
       0: invokedynamic #611,  0            // InvokeDynamic #1:apply:()Ljava/util/function/BiFunction;
       5: invokestatic  #614                // Method net/minecraft/util/Util.memoize:(Ljava/util/function/BiFunction;)Ljava/util/function/BiFunction;
       8: putstatic     #277                // Field OUTLINE:Ljava/util/function/BiFunction;
      11: invokedynamic #624,  0            // InvokeDynamic #2:get:()Ljava/util/function/Supplier;
      16: putstatic     #626                // Field MOVING_BLOCK_SAMPLER:Ljava/util/function/Supplier;
      19: ldc_w         #628                // String solid_moving_block
      22: getstatic     #631                // Field net/minecraft/client/renderer/RenderPipelines.SOLID_BLOCK:Lcom/mojang/blaze3d/pipeline/RenderPipeline;
      25: invokestatic  #125                // Method net/minecraft/client/renderer/rendertype/RenderSetup.builder:(Lcom/mojang/blaze3d/pipeline/RenderPipeline;)Lnet/minecraft/client/renderer/rendertype/RenderSetup$RenderSetupBuilder;
      28: invokevirtual #135                // Method net/minecraft/client/renderer/rendertype/RenderSetup$RenderSetupBuilder.useLightmap:()Lnet/minecraft/client/renderer/rendertype/RenderSetup$RenderSetupBuilder;
      31: ldc           #127                // String Sampler0
      33: getstatic     #636                // Field net/minecraft/client/renderer/texture/TextureAtlas.LOCATION_BLOCKS:Lnet/minecraft/resources/Identifier;
      36: getstatic     #626                // Field MOVING_BLOCK_SAMPLER:Ljava/util/function/Supplier;
      39: invokevirtual #639                // Method net/minecraft/client/renderer/rendertype/RenderSetup$RenderSetupBuilder.withTexture:(Ljava/lang/String;Lnet/minecraft/resources/Identifier;Ljava/util/function/Supplier;)Lnet/minecraft/client/renderer/rendertype/RenderSetup$RenderSetupBuilder;
      42: invokevirtual #151                // Method net/minecraft/client/renderer/rendertype/RenderSetup$RenderSetupBuilder.affectsCrumbling:()Lnet/minecraft/client/renderer/rendertype/RenderSetup$RenderSetupBuilder;
      45: getstatic     #155                // Field net/minecraft/client/renderer/rendertype/RenderSetup$OutlineProperty.AFFECTS_OUTLINE:Lnet/minecraft/client/renderer/rendertype/RenderSetup$OutlineProperty;
      48: invokevirtual #159                // Method net/minecraft/client/renderer/rendertype/RenderSetup$RenderSetupBuilder.setOutline:(Lnet/minecraft/client/renderer/rendertype/RenderSetup$OutlineProperty;)Lnet/minecraft/client/renderer/rendertype/RenderSetup$RenderSetupBuilder;
      51: invokevirtual #163                // Method net/minecraft/client/renderer/rendertype/RenderSetup$RenderSetupBuilder.createRenderSetup:()Lnet/minecraft/client/renderer/rendertype/RenderSetup;
      54: invokestatic  #169                // Method net/minecraft/client/renderer/rendertype/RenderType.create:(Ljava/lang/String;Lnet/minecraft/client/renderer/rendertype/RenderSetup;)Lnet/minecraft/client/renderer/rendertype/RenderType;
      57: putstatic     #94                 // Field SOLID_MOVING_BLOCK:Lnet/minecraft/client/renderer/rendertype/RenderType;
      60: ldc_w         #641                // String cutout_moving_block
      63: getstatic     #644                // Field net/minecraft/client/renderer/RenderPipelines.CUTOUT_BLOCK:Lcom/mojang/blaze3d/pipeline/RenderPipeline;
      66: invokestatic  #125                // Method net/minecraft/client/renderer/rendertype/RenderSetup.builder:(Lcom/mojang/blaze3d/pipeline/RenderPipeline;)Lnet/minecraft/client/renderer/rendertype/RenderSetup$RenderSetupBuilder;
      69: invokevirtual #135                // Method net/minecraft/client/renderer/rendertype/RenderSetup$RenderSetupBuilder.useLightmap:()Lnet/minecraft/client/renderer/rendertype/RenderSetup$RenderSetupBuilder;
      72: ldc           #127                // String Sampler0
      74: getstatic     #636                // Field net/minecraft/client/renderer/texture/TextureAtlas.LOCATION_BLOCKS:Lnet/minecraft/resources/Identifier;
      77: getstatic     #626                // Field MOVING_BLOCK_SAMPLER:Ljava/util/function/Supplier;
      80: invokevirtual #639                // Method net/minecraft/client/renderer/rendertype/RenderSetup$RenderSetupBuilder.withTexture:(Ljava/lang/String;Lnet/minecraft/resources/Identifier;Ljava/util/function/Supplier;)Lnet/minecraft/client/renderer/rendertype/RenderSetup$RenderSetupBuilder;
      83: invokevirtual #151                // Method net/minecraft/client/renderer/rendertype/RenderSetup$RenderSetupBuilder.affectsCrumbling:()Lnet/minecraft/client/renderer/rendertype/RenderSetup$RenderSetupBuilder;
      86: getstatic     #155                // Field net/minecraft/client/renderer/rendertype/RenderSetup$OutlineProperty.AFFECTS_OUTLINE:Lnet/minecraft/client/renderer/rendertype/RenderSetup$OutlineProperty;
      89: invokevirtual #159                // Method net/minecraft/client/renderer/rendertype/RenderSetup$RenderSetupBuilder.setOutline:(Lnet/minecraft/client/renderer/rendertype/RenderSetup$OutlineProperty;)Lnet/minecraft/client/renderer/rendertype/RenderSetup$RenderSetupBuilder;
      92: invokevirtual #163                // Method net/minecraft/client/renderer/rendertype/RenderSetup$RenderSetupBuilder.createRenderSetup:()Lnet/minecraft/client/renderer/rendertype/RenderSetup;
      95: invokestatic  #169                // Method net/minecraft/client/renderer/rendertype/RenderType.create:(Ljava/lang/String;Lnet/minecraft/client/renderer/rendertype/RenderSetup;)Lnet/minecraft/client/renderer/rendertype/RenderType;
      98: putstatic     #97                 // Field CUTOUT_MOVING_BLOCK:Lnet/minecraft/client/renderer/rendertype/RenderType;
     101: ldc_w         #646                // String translucent_moving_block
     104: getstatic     #648                // Field net/minecraft/client/renderer/RenderPipelines.TRANSLUCENT_MOVING_BLOCK:Lcom/mojang/blaze3d/pipeline/RenderPipeline;
     107: invokestatic  #125                // Method net/minecraft/client/renderer/rendertype/RenderSetup.builder:(Lcom/mojang/blaze3d/pipeline/RenderPipeline;)Lnet/minecraft/client/renderer/rendertype/RenderSetup$RenderSetupBuilder;
     110: invokevirtual #135                // Method net/minecraft/client/renderer/rendertype/RenderSetup$RenderSetupBuilder.useLightmap:()Lnet/minecraft/client/renderer/rendertype/RenderSetup$RenderSetupBuilder;
     113: ldc           #127                // String Sampler0
     115: getstatic     #636                // Field net/minecraft/client/renderer/texture/TextureAtlas.LOCATION_BLOCKS:Lnet/minecraft/resources/Identifier;
     118: getstatic     #626                // Field MOVING_BLOCK_SAMPLER:Ljava/util/function/Supplier;
     121: invokevirtual #639                // Method net/minecraft/client/renderer/rendertype/RenderSetup$RenderSetupBuilder.withTexture:(Ljava/lang/String;Lnet/minecraft/resources/Identifier;Ljava/util/function/Supplier;)Lnet/minecraft/client/renderer/rendertype/RenderSetup$RenderSetupBuilder;
     124: getstatic     #515                // Field net/minecraft/client/renderer/rendertype/OutputTarget.ITEM_ENTITY_TARGET:Lnet/minecraft/client/renderer/rendertype/OutputTarget;
     127: invokevirtual #413                // Method net/minecraft/client/renderer/rendertype/RenderSetup$RenderSetupBuilder.setOutputTarget:(Lnet/minecraft/client/renderer/rendertype/OutputTarget;)Lnet/minecraft/client/renderer/rendertype/RenderSetup$RenderSetupBuilder;
     130: invokevirtual #261                // Method net/minecraft/client/renderer/rendertype/RenderSetup$RenderSetupBuilder.sortOnUpload:()Lnet/minecraft/client/renderer/rendertype/RenderSetup$RenderSetupBuilder;
     133: ldc_w         #437                // int 786432
     136: invokevirtual #441                // Method net/minecraft/client/renderer/rendertype/RenderSetup$RenderSetupBuilder.bufferSize:(I)Lnet/minecraft/client/renderer/rendertype/RenderSetup$RenderSetupBuilder;
     139: getstatic     #155                // Field net/minecraft/client/renderer/rendertype/RenderSetup$OutlineProperty.AFFECTS_OUTLINE:Lnet/minecraft/client/renderer/rendertype/RenderSetup$OutlineProperty;
     142: invokevirtual #159                // Method net/minecraft/client/renderer/rendertype/RenderSetup$RenderSetupBuilder.setOutline:(Lnet/minecraft/client/renderer/rendertype/RenderSetup$OutlineProperty;)Lnet/minecraft/client/renderer/rendertype/RenderSetup$RenderSetupBuilder;
     145: invokevirtual #163                // Method net/minecraft/client/renderer/rendertype/RenderSetup$RenderSetupBuilder.createRenderSetup:()Lnet/minecraft/client/renderer/rendertype/RenderSetup;
     148: invokestatic  #169                // Method net/minecraft/client/renderer/rendertype/RenderType.create:(Ljava/lang/String;Lnet/minecraft/client/renderer/rendertype/RenderSetup;)Lnet/minecraft/client/renderer/rendertype/RenderType;
     151: putstatic     #100                // Field TRANSLUCENT_MOVING_BLOCK:Lnet/minecraft/client/renderer/rendertype/RenderType;
     154: invokedynamic #654,  0            // InvokeDynamic #3:apply:()Ljava/util/function/Function;
     159: invokestatic  #381                // Method net/minecraft/util/Util.memoize:(Ljava/util/function/Function;)Ljava/util/function/Function;
     162: putstatic     #105                // Field ARMOR_CUTOUT_NO_CULL:Ljava/util/function/Function;
     165: invokedynamic #658,  0            // InvokeDynamic #4:apply:()Ljava/util/function/Function;
     170: invokestatic  #381                // Method net/minecraft/util/Util.memoize:(Ljava/util/function/Function;)Ljava/util/function/Function;
     173: putstatic     #174                // Field ARMOR_TRANSLUCENT:Ljava/util/function/Function;
     176: invokedynamic #662,  0            // InvokeDynamic #5:apply:()Ljava/util/function/Function;
     181: invokestatic  #381                // Method net/minecraft/util/Util.memoize:(Ljava/util/function/Function;)Ljava/util/function/Function;
     184: putstatic     #177                // Field ENTITY_SOLID:Ljava/util/function/Function;
     187: invokedynamic #666,  0            // InvokeDynamic #6:apply:()Ljava/util/function/Function;
     192: invokestatic  #381                // Method net/minecraft/util/Util.memoize:(Ljava/util/function/Function;)Ljava/util/function/Function;
     195: putstatic     #180                // Field ENTITY_SOLID_Z_OFFSET_FORWARD:Ljava/util/function/Function;
     198: invokedynamic #670,  0            // InvokeDynamic #7:apply:()Ljava/util/function/Function;
     203: invokestatic  #381                // Method net/minecraft/util/Util.memoize:(Ljava/util/function/Function;)Ljava/util/function/Function;
     206: putstatic     #183                // Field ENTITY_CUTOUT:Ljava/util/function/Function;
     209: invokedynamic #674,  0            // InvokeDynamic #8:apply:()Ljava/util/function/BiFunction;
     214: invokestatic  #614                // Method net/minecraft/util/Util.memoize:(Ljava/util/function/BiFunction;)Ljava/util/function/BiFunction;
     217: putstatic     #188                // Field ENTITY_CUTOUT_NO_CULL:Ljava/util/function/BiFunction;
     220: invokedynamic #678,  0            // InvokeDynamic #9:apply:()Ljava/util/function/BiFunction;
     225: invokestatic  #614                // Method net/minecraft/util/Util.memoize:(Ljava/util/function/BiFunction;)Ljava/util/function/BiFunction;
     228: putstatic     #205                // Field ENTITY_CUTOUT_NO_CULL_Z_OFFSET:Ljava/util/function/BiFunction;
     231: invokedynamic #682,  0            // InvokeDynamic #10:apply:()Ljava/util/function/Function;
     236: invokestatic  #381                // Method net/minecraft/util/Util.memoize:(Ljava/util/function/Function;)Ljava/util/function/Function;
     239: putstatic     #210                // Field ITEM_ENTITY_TRANSLUCENT_CULL:Ljava/util/function/Function;
     242: invokedynamic #686,  0            // InvokeDynamic #11:apply:()Ljava/util/function/BiFunction;
     247: invokestatic  #614                // Method net/minecraft/util/Util.memoize:(Ljava/util/function/BiFunction;)Ljava/util/function/BiFunction;
     250: putstatic     #213                // Field ENTITY_TRANSLUCENT:Ljava/util/function/BiFunction;
     253: invokedynamic #690,  0            // InvokeDynamic #12:apply:()Ljava/util/function/BiFunction;
     258: invokestatic  #614                // Method net/minecraft/util/Util.memoize:(Ljava/util/function/BiFunction;)Ljava/util/function/BiFunction;
     261: putstatic     #218                // Field ENTITY_TRANSLUCENT_EMISSIVE:Ljava/util/function/BiFunction;
     264: invokedynamic #694,  0            // InvokeDynamic #13:apply:()Ljava/util/function/Function;
     269: invokestatic  #381                // Method net/minecraft/util/Util.memoize:(Ljava/util/function/Function;)Ljava/util/function/Function;
     272: putstatic     #223                // Field ENTITY_SMOOTH_CUTOUT:Ljava/util/function/Function;
     275: invokedynamic #698,  0            // InvokeDynamic #14:apply:()Ljava/util/function/BiFunction;
     280: invokestatic  #614                // Method net/minecraft/util/Util.memoize:(Ljava/util/function/BiFunction;)Ljava/util/function/BiFunction;
     283: putstatic     #226                // Field BEACON_BEAM:Ljava/util/function/BiFunction;
     286: invokedynamic #702,  0            // InvokeDynamic #15:apply:()Ljava/util/function/Function;
     291: invokestatic  #381                // Method net/minecraft/util/Util.memoize:(Ljava/util/function/Function;)Ljava/util/function/Function;
     294: putstatic     #229                // Field ENTITY_DECAL:Ljava/util/function/Function;
     297: invokedynamic #706,  0            // InvokeDynamic #16:apply:()Ljava/util/function/Function;
     302: invokestatic  #381                // Method net/minecraft/util/Util.memoize:(Ljava/util/function/Function;)Ljava/util/function/Function;
     305: putstatic     #232                // Field ENTITY_NO_OUTLINE:Ljava/util/function/Function;
     308: invokedynamic #710,  0            // InvokeDynamic #17:apply:()Ljava/util/function/Function;
     313: invokestatic  #381                // Method net/minecraft/util/Util.memoize:(Ljava/util/function/Function;)Ljava/util/function/Function;
     316: putstatic     #235                // Field ENTITY_SHADOW:Ljava/util/function/Function;
     319: invokedynamic #714,  0            // InvokeDynamic #18:apply:()Ljava/util/function/Function;
     324: invokestatic  #381                // Method net/minecraft/util/Util.memoize:(Ljava/util/function/Function;)Ljava/util/function/Function;
     327: putstatic     #238                // Field DRAGON_EXPLOSION_ALPHA:Ljava/util/function/Function;
     330: invokedynamic #718,  0            // InvokeDynamic #19:apply:()Ljava/util/function/Function;
     335: invokestatic  #381                // Method net/minecraft/util/Util.memoize:(Ljava/util/function/Function;)Ljava/util/function/Function;
     338: putstatic     #241                // Field EYES:Ljava/util/function/Function;
     341: ldc_w         #719                // String leash
     344: getstatic     #721                // Field net/minecraft/client/renderer/RenderPipelines.LEASH:Lcom/mojang/blaze3d/pipeline/RenderPipeline;
     347: invokestatic  #125                // Method net/minecraft/client/renderer/rendertype/RenderSetup.builder:(Lcom/mojang/blaze3d/pipeline/RenderPipeline;)Lnet/minecraft/client/renderer/rendertype/RenderSetup$RenderSetupBuilder;
     350: invokevirtual #135                // Method net/minecraft/client/renderer/rendertype/RenderSetup$RenderSetupBuilder.useLightmap:()Lnet/minecraft/client/renderer/rendertype/RenderSetup$RenderSetupBuilder;
     353: invokevirtual #163                // Method net/minecraft/client/renderer/rendertype/RenderSetup$RenderSetupBuilder.createRenderSetup:()Lnet/minecraft/client/renderer/rendertype/RenderSetup;
     356: invokestatic  #169                // Method net/minecraft/client/renderer/rendertype/RenderType.create:(Ljava/lang/String;Lnet/minecraft/client/renderer/rendertype/RenderSetup;)Lnet/minecraft/client/renderer/rendertype/RenderType;
     359: putstatic     #271                // Field LEASH:Lnet/minecraft/client/renderer/rendertype/RenderType;
     362: ldc_w         #723                // String water_mask
     365: getstatic     #725                // Field net/minecraft/client/renderer/RenderPipelines.WATER_MASK:Lcom/mojang/blaze3d/pipeline/RenderPipeline;
     368: invokestatic  #125                // Method net/minecraft/client/renderer/rendertype/RenderSetup.builder:(Lcom/mojang/blaze3d/pipeline/RenderPipeline;)Lnet/minecraft/client/renderer/rendertype/RenderSetup$RenderSetupBuilder;
     371: invokevirtual #163                // Method net/minecraft/client/renderer/rendertype/RenderSetup$RenderSetupBuilder.createRenderSetup:()Lnet/minecraft/client/renderer/rendertype/RenderSetup;
     374: invokestatic  #169                // Method net/minecraft/client/renderer/rendertype/RenderType.create:(Ljava/lang/String;Lnet/minecraft/client/renderer/rendertype/RenderSetup;)Lnet/minecraft/client/renderer/rendertype/RenderType;
     377: putstatic     #274                // Field WATER_MASK:Lnet/minecraft/client/renderer/rendertype/RenderType;
     380: ldc_w         #727                // String armor_entity_glint
     383: getstatic     #729                // Field net/minecraft/client/renderer/RenderPipelines.GLINT:Lcom/mojang/blaze3d/pipeline/RenderPipeline;
     386: invokestatic  #125                // Method net/minecraft/client/renderer/rendertype/RenderSetup.builder:(Lcom/mojang/blaze3d/pipeline/RenderPipeline;)Lnet/minecraft/client/renderer/rendertype/RenderSetup$RenderSetupBuilder;
     389: ldc           #127                // String Sampler0
     391: getstatic     #734                // Field net/minecraft/client/renderer/entity/ItemRenderer.ENCHANTED_GLINT_ARMOR:Lnet/minecraft/resources/Identifier;
     394: invokevirtual #131                // Method net/minecraft/client/renderer/rendertype/RenderSetup$RenderSetupBuilder.withTexture:(Ljava/lang/String;Lnet/minecraft/resources/Identifier;)Lnet/minecraft/client/renderer/rendertype/RenderSetup$RenderSetupBuilder;
     397: getstatic     #738                // Field net/minecraft/client/renderer/rendertype/TextureTransform.ARMOR_ENTITY_GLINT_TEXTURING:Lnet/minecraft/client/renderer/rendertype/TextureTransform;
     400: invokevirtual #258                // Method net/minecraft/client/renderer/rendertype/RenderSetup$RenderSetupBuilder.setTextureTransform:(Lnet/minecraft/client/renderer/rendertype/TextureTransform;)Lnet/minecraft/client/renderer/rendertype/RenderSetup$RenderSetupBuilder;
     403: getstatic     #144                // Field net/minecraft/client/renderer/rendertype/LayeringTransform.VIEW_OFFSET_Z_LAYERING:Lnet/minecraft/client/renderer/rendertype/LayeringTransform;
     406: invokevirtual #148                // Method net/minecraft/client/renderer/rendertype/RenderSetup$RenderSetupBuilder.setLayeringTransform:(Lnet/minecraft/client/renderer/rendertype/LayeringTransform;)Lnet/minecraft/client/renderer/rendertype/RenderSetup$RenderSetupBuilder;
     409: invokevirtual #163                // Method net/minecraft/client/renderer/rendertype/RenderSetup$RenderSetupBuilder.createRenderSetup:()Lnet/minecraft/client/renderer/rendertype/RenderSetup;
     412: invokestatic  #169                // Method net/minecraft/client/renderer/rendertype/RenderType.create:(Ljava/lang/String;Lnet/minecraft/client/renderer/rendertype/RenderSetup;)Lnet/minecraft/client/renderer/rendertype/RenderType;
     415: putstatic     #280                // Field ARMOR_ENTITY_GLINT:Lnet/minecraft/client/renderer/rendertype/RenderType;
     418: ldc_w         #740                // String glint_translucent
     421: getstatic     #729                // Field net/minecraft/client/renderer/RenderPipelines.GLINT:Lcom/mojang/blaze3d/pipeline/RenderPipeline;
     424: invokestatic  #125                // Method net/minecraft/client/renderer/rendertype/RenderSetup.builder:(Lcom/mojang/blaze3d/pipeline/RenderPipeline;)Lnet/minecraft/client/renderer/rendertype/RenderSetup$RenderSetupBuilder;
     427: ldc           #127                // String Sampler0
     429: getstatic     #743                // Field net/minecraft/client/renderer/entity/ItemRenderer.ENCHANTED_GLINT_ITEM:Lnet/minecraft/resources/Identifier;
     432: invokevirtual #131                // Method net/minecraft/client/renderer/rendertype/RenderSetup$RenderSetupBuilder.withTexture:(Ljava/lang/String;Lnet/minecraft/resources/Identifier;)Lnet/minecraft/client/renderer/rendertype/RenderSetup$RenderSetupBuilder;
     435: getstatic     #746                // Field net/minecraft/client/renderer/rendertype/TextureTransform.GLINT_TEXTURING:Lnet/minecraft/client/renderer/rendertype/TextureTransform;
     438: invokevirtual #258                // Method net/minecraft/client/renderer/rendertype/RenderSetup$RenderSetupBuilder.setTextureTransform:(Lnet/minecraft/client/renderer/rendertype/TextureTransform;)Lnet/minecraft/client/renderer/rendertype/RenderSetup$RenderSetupBuilder;
     441: getstatic     #515                // Field net/minecraft/client/renderer/rendertype/OutputTarget.ITEM_ENTITY_TARGET:Lnet/minecraft/client/renderer/rendertype/OutputTarget;
     444: invokevirtual #413                // Method net/minecraft/client/renderer/rendertype/RenderSetup$RenderSetupBuilder.setOutputTarget:(Lnet/minecraft/client/renderer/rendertype/OutputTarget;)Lnet/minecraft/client/renderer/rendertype/RenderSetup$RenderSetupBuilder;
     447: invokevirtual #163                // Method net/minecraft/client/renderer/rendertype/RenderSetup$RenderSetupBuilder.createRenderSetup:()Lnet/minecraft/client/renderer/rendertype/RenderSetup;
     450: invokestatic  #169                // Method net/minecraft/client/renderer/rendertype/RenderType.create:(Ljava/lang/String;Lnet/minecraft/client/renderer/rendertype/RenderSetup;)Lnet/minecraft/client/renderer/rendertype/RenderType;
     453: putstatic     #283                // Field GLINT_TRANSLUCENT:Lnet/minecraft/client/renderer/rendertype/RenderType;
     456: ldc_w         #747                // String glint
     459: getstatic     #729                // Field net/minecraft/client/renderer/RenderPipelines.GLINT:Lcom/mojang/blaze3d/pipeline/RenderPipeline;
     462: invokestatic  #125                // Method net/minecraft/client/renderer/rendertype/RenderSetup.builder:(Lcom/mojang/blaze3d/pipeline/RenderPipeline;)Lnet/minecraft/client/renderer/rendertype/RenderSetup$RenderSetupBuilder;
     465: ldc           #127                // String Sampler0
     467: getstatic     #743                // Field net/minecraft/client/renderer/entity/ItemRenderer.ENCHANTED_GLINT_ITEM:Lnet/minecraft/resources/Identifier;
     470: invokevirtual #131                // Method net/minecraft/client/renderer/rendertype/RenderSetup$RenderSetupBuilder.withTexture:(Ljava/lang/String;Lnet/minecraft/resources/Identifier;)Lnet/minecraft/client/renderer/rendertype/RenderSetup$RenderSetupBuilder;
     473: getstatic     #746                // Field net/minecraft/client/renderer/rendertype/TextureTransform.GLINT_TEXTURING:Lnet/minecraft/client/renderer/rendertype/TextureTransform;
     476: invokevirtual #258                // Method net/minecraft/client/renderer/rendertype/RenderSetup$RenderSetupBuilder.setTextureTransform:(Lnet/minecraft/client/renderer/rendertype/TextureTransform;)Lnet/minecraft/client/renderer/rendertype/RenderSetup$RenderSetupBuilder;
     479: invokevirtual #163                // Method net/minecraft/client/renderer/rendertype/RenderSetup$RenderSetupBuilder.createRenderSetup:()Lnet/minecraft/client/renderer/rendertype/RenderSetup;
     482: invokestatic  #169                // Method net/minecraft/client/renderer/rendertype/RenderType.create:(Ljava/lang/String;Lnet/minecraft/client/renderer/rendertype/RenderSetup;)Lnet/minecraft/client/renderer/rendertype/RenderType;
     485: putstatic     #286                // Field GLINT:Lnet/minecraft/client/renderer/rendertype/RenderType;
     488: ldc_w         #749                // String entity_glint
     491: getstatic     #729                // Field net/minecraft/client/renderer/RenderPipelines.GLINT:Lcom/mojang/blaze3d/pipeline/RenderPipeline;
     494: invokestatic  #125                // Method net/minecraft/client/renderer/rendertype/RenderSetup.builder:(Lcom/mojang/blaze3d/pipeline/RenderPipeline;)Lnet/minecraft/client/renderer/rendertype/RenderSetup$RenderSetupBuilder;
     497: ldc           #127                // String Sampler0
     499: getstatic     #743                // Field net/minecraft/client/renderer/entity/ItemRenderer.ENCHANTED_GLINT_ITEM:Lnet/minecraft/resources/Identifier;
     502: invokevirtual #131                // Method net/minecraft/client/renderer/rendertype/RenderSetup$RenderSetupBuilder.withTexture:(Ljava/lang/String;Lnet/minecraft/resources/Identifier;)Lnet/minecraft/client/renderer/rendertype/RenderSetup$RenderSetupBuilder;
     505: getstatic     #752                // Field net/minecraft/client/renderer/rendertype/TextureTransform.ENTITY_GLINT_TEXTURING:Lnet/minecraft/client/renderer/rendertype/TextureTransform;
     508: invokevirtual #258                // Method net/minecraft/client/renderer/rendertype/RenderSetup$RenderSetupBuilder.setTextureTransform:(Lnet/minecraft/client/renderer/rendertype/TextureTransform;)Lnet/minecraft/client/renderer/rendertype/RenderSetup$RenderSetupBuilder;
     511: invokevirtual #163                // Method net/minecraft/client/renderer/rendertype/RenderSetup$RenderSetupBuilder.createRenderSetup:()Lnet/minecraft/client/renderer/rendertype/RenderSetup;
     514: invokestatic  #169                // Method net/minecraft/client/renderer/rendertype/RenderType.create:(Ljava/lang/String;Lnet/minecraft/client/renderer/rendertype/RenderSetup;)Lnet/minecraft/client/renderer/rendertype/RenderType;
     517: putstatic     #289                // Field ENTITY_GLINT:Lnet/minecraft/client/renderer/rendertype/RenderType;
     520: invokedynamic #756,  0            // InvokeDynamic #20:apply:()Ljava/util/function/Function;
     525: invokestatic  #381                // Method net/minecraft/util/Util.memoize:(Ljava/util/function/Function;)Ljava/util/function/Function;
     528: putstatic     #292                // Field CRUMBLING:Ljava/util/function/Function;
     531: invokedynamic #760,  0            // InvokeDynamic #21:apply:()Ljava/util/function/Function;
     536: invokestatic  #381                // Method net/minecraft/util/Util.memoize:(Ljava/util/function/Function;)Ljava/util/function/Function;
     539: putstatic     #295                // Field TEXT:Ljava/util/function/Function;
     542: ldc_w         #762                // String text_background
     545: getstatic     #764                // Field net/minecraft/client/renderer/RenderPipelines.TEXT_BACKGROUND:Lcom/mojang/blaze3d/pipeline/RenderPipeline;
     548: invokestatic  #125                // Method net/minecraft/client/renderer/rendertype/RenderSetup.builder:(Lcom/mojang/blaze3d/pipeline/RenderPipeline;)Lnet/minecraft/client/renderer/rendertype/RenderSetup$RenderSetupBuilder;
     551: invokevirtual #135                // Method net/minecraft/client/renderer/rendertype/RenderSetup$RenderSetupBuilder.useLightmap:()Lnet/minecraft/client/renderer/rendertype/RenderSetup$RenderSetupBuilder;
     554: invokevirtual #261                // Method net/minecraft/client/renderer/rendertype/RenderSetup$RenderSetupBuilder.sortOnUpload:()Lnet/minecraft/client/renderer/rendertype/RenderSetup$RenderSetupBuilder;
     557: invokevirtual #163                // Method net/minecraft/client/renderer/rendertype/RenderSetup$RenderSetupBuilder.createRenderSetup:()Lnet/minecraft/client/renderer/rendertype/RenderSetup;
     560: invokestatic  #169                // Method net/minecraft/client/renderer/rendertype/RenderType.create:(Ljava/lang/String;Lnet/minecraft/client/renderer/rendertype/RenderSetup;)Lnet/minecraft/client/renderer/rendertype/RenderType;
     563: putstatic     #298                // Field TEXT_BACKGROUND:Lnet/minecraft/client/renderer/rendertype/RenderType;
     566: invokedynamic #768,  0            // InvokeDynamic #22:apply:()Ljava/util/function/Function;
     571: invokestatic  #381                // Method net/minecraft/util/Util.memoize:(Ljava/util/function/Function;)Ljava/util/function/Function;
     574: putstatic     #301                // Field TEXT_INTENSITY:Ljava/util/function/Function;
     577: invokedynamic #772,  0            // InvokeDynamic #23:apply:()Ljava/util/function/Function;
     582: invokestatic  #381                // Method net/minecraft/util/Util.memoize:(Ljava/util/function/Function;)Ljava/util/function/Function;
     585: putstatic     #304                // Field TEXT_POLYGON_OFFSET:Ljava/util/function/Function;
     588: invokedynamic #776,  0            // InvokeDynamic #24:apply:()Ljava/util/function/Function;
     593: invokestatic  #381                // Method net/minecraft/util/Util.memoize:(Ljava/util/function/Function;)Ljava/util/function/Function;
     596: putstatic     #307                // Field TEXT_INTENSITY_POLYGON_OFFSET:Ljava/util/function/Function;
     599: invokedynamic #780,  0            // InvokeDynamic #25:apply:()Ljava/util/function/Function;
     604: invokestatic  #381                // Method net/minecraft/util/Util.memoize:(Ljava/util/function/Function;)Ljava/util/function/Function;
     607: putstatic     #310                // Field TEXT_SEE_THROUGH:Ljava/util/function/Function;
     610: ldc_w         #782                // String text_background_see_through
     613: getstatic     #784                // Field net/minecraft/client/renderer/RenderPipelines.TEXT_BACKGROUND_SEE_THROUGH:Lcom/mojang/blaze3d/pipeline/RenderPipeline;
     616: invokestatic  #125                // Method net/minecraft/client/renderer/rendertype/RenderSetup.builder:(Lcom/mojang/blaze3d/pipeline/RenderPipeline;)Lnet/minecraft/client/renderer/rendertype/RenderSetup$RenderSetupBuilder;
     619: invokevirtual #135                // Method net/minecraft/client/renderer/rendertype/RenderSetup$RenderSetupBuilder.useLightmap:()Lnet/minecraft/client/renderer/rendertype/RenderSetup$RenderSetupBuilder;
     622: invokevirtual #261                // Method net/minecraft/client/renderer/rendertype/RenderSetup$RenderSetupBuilder.sortOnUpload:()Lnet/minecraft/client/renderer/rendertype/RenderSetup$RenderSetupBuilder;
     625: invokevirtual #163                // Method net/minecraft/client/renderer/rendertype/RenderSetup$RenderSetupBuilder.createRenderSetup:()Lnet/minecraft/client/renderer/rendertype/RenderSetup;
     628: invokestatic  #169                // Method net/minecraft/client/renderer/rendertype/RenderType.create:(Ljava/lang/String;Lnet/minecraft/client/renderer/rendertype/RenderSetup;)Lnet/minecraft/client/renderer/rendertype/RenderType;
     631: putstatic     #313                // Field TEXT_BACKGROUND_SEE_THROUGH:Lnet/minecraft/client/renderer/rendertype/RenderType;
     634: invokedynamic #788,  0            // InvokeDynamic #26:apply:()Ljava/util/function/Function;
     639: invokestatic  #381                // Method net/minecraft/util/Util.memoize:(Ljava/util/function/Function;)Ljava/util/function/Function;
     642: putstatic     #316                // Field TEXT_INTENSITY_SEE_THROUGH:Ljava/util/function/Function;
     645: ldc_w         #789                // String lightning
     648: getstatic     #791                // Field net/minecraft/client/renderer/RenderPipelines.LIGHTNING:Lcom/mojang/blaze3d/pipeline/RenderPipeline;
     651: invokestatic  #125                // Method net/minecraft/client/renderer/rendertype/RenderSetup.builder:(Lcom/mojang/blaze3d/pipeline/RenderPipeline;)Lnet/minecraft/client/renderer/rendertype/RenderSetup$RenderSetupBuilder;
     654: getstatic     #409                // Field net/minecraft/client/renderer/rendertype/OutputTarget.WEATHER_TARGET:Lnet/minecraft/client/renderer/rendertype/OutputTarget;
     657: invokevirtual #413                // Method net/minecraft/client/renderer/rendertype/RenderSetup$RenderSetupBuilder.setOutputTarget:(Lnet/minecraft/client/renderer/rendertype/OutputTarget;)Lnet/minecraft/client/renderer/rendertype/RenderSetup$RenderSetupBuilder;
     660: invokevirtual #261                // Method net/minecraft/client/renderer/rendertype/RenderSetup$RenderSetupBuilder.sortOnUpload:()Lnet/minecraft/client/renderer/rendertype/RenderSetup$RenderSetupBuilder;
     663: invokevirtual #163                // Method net/minecraft/client/renderer/rendertype/RenderSetup$RenderSetupBuilder.createRenderSetup:()Lnet/minecraft/client/renderer/rendertype/RenderSetup;
     666: invokestatic  #169                // Method net/minecraft/client/renderer/rendertype/RenderType.create:(Ljava/lang/String;Lnet/minecraft/client/renderer/rendertype/RenderSetup;)Lnet/minecraft/client/renderer/rendertype/RenderType;
     669: putstatic     #319                // Field LIGHTNING:Lnet/minecraft/client/renderer/rendertype/RenderType;
     672: ldc_w         #793                // String dragon_rays
     675: getstatic     #795                // Field net/minecraft/client/renderer/RenderPipelines.DRAGON_RAYS:Lcom/mojang/blaze3d/pipeline/RenderPipeline;
     678: invokestatic  #125                // Method net/minecraft/client/renderer/rendertype/RenderSetup.builder:(Lcom/mojang/blaze3d/pipeline/RenderPipeline;)Lnet/minecraft/client/renderer/rendertype/RenderSetup$RenderSetupBuilder;
     681: invokevirtual #163                // Method net/minecraft/client/renderer/rendertype/RenderSetup$RenderSetupBuilder.createRenderSetup:()Lnet/minecraft/client/renderer/rendertype/RenderSetup;
     684: invokestatic  #169                // Method net/minecraft/client/renderer/rendertype/RenderType.create:(Ljava/lang/String;Lnet/minecraft/client/renderer/rendertype/RenderSetup;)Lnet/minecraft/client/renderer/rendertype/RenderType;
     687: putstatic     #322                // Field DRAGON_RAYS:Lnet/minecraft/client/renderer/rendertype/RenderType;
     690: ldc_w         #797                // String dragon_rays_depth
     693: getstatic     #799                // Field net/minecraft/client/renderer/RenderPipelines.DRAGON_RAYS_DEPTH:Lcom/mojang/blaze3d/pipeline/RenderPipeline;
     696: invokestatic  #125                // Method net/minecraft/client/renderer/rendertype/RenderSetup.builder:(Lcom/mojang/blaze3d/pipeline/RenderPipeline;)Lnet/minecraft/client/renderer/rendertype/RenderSetup$RenderSetupBuilder;
     699: invokevirtual #163                // Method net/minecraft/client/renderer/rendertype/RenderSetup$RenderSetupBuilder.createRenderSetup:()Lnet/minecraft/client/renderer/rendertype/RenderSetup;
     702: invokestatic  #169                // Method net/minecraft/client/renderer/rendertype/RenderType.create:(Ljava/lang/String;Lnet/minecraft/client/renderer/rendertype/RenderSetup;)Lnet/minecraft/client/renderer/rendertype/RenderType;
     705: putstatic     #325                // Field DRAGON_RAYS_DEPTH:Lnet/minecraft/client/renderer/rendertype/RenderType;
     708: ldc_w         #801                // String tripwire_moving_block
     711: getstatic     #804                // Field net/minecraft/client/renderer/RenderPipelines.TRIPWIRE_BLOCK:Lcom/mojang/blaze3d/pipeline/RenderPipeline;
     714: invokestatic  #125                // Method net/minecraft/client/renderer/rendertype/RenderSetup.builder:(Lcom/mojang/blaze3d/pipeline/RenderPipeline;)Lnet/minecraft/client/renderer/rendertype/RenderSetup$RenderSetupBuilder;
     717: invokevirtual #135                // Method net/minecraft/client/renderer/rendertype/RenderSetup$RenderSetupBuilder.useLightmap:()Lnet/minecraft/client/renderer/rendertype/RenderSetup$RenderSetupBuilder;
     720: ldc           #127                // String Sampler0
     722: getstatic     #636                // Field net/minecraft/client/renderer/texture/TextureAtlas.LOCATION_BLOCKS:Lnet/minecraft/resources/Identifier;
     725: getstatic     #626                // Field MOVING_BLOCK_SAMPLER:Ljava/util/function/Supplier;
     728: invokevirtual #639                // Method net/minecraft/client/renderer/rendertype/RenderSetup$RenderSetupBuilder.withTexture:(Ljava/lang/String;Lnet/minecraft/resources/Identifier;Ljava/util/function/Supplier;)Lnet/minecraft/client/renderer/rendertype/RenderSetup$RenderSetupBuilder;
     731: getstatic     #409                // Field net/minecraft/client/renderer/rendertype/OutputTarget.WEATHER_TARGET:Lnet/minecraft/client/renderer/rendertype/OutputTarget;
     734: invokevirtual #413                // Method net/minecraft/client/renderer/rendertype/RenderSetup$RenderSetupBuilder.setOutputTarget:(Lnet/minecraft/client/renderer/rendertype/OutputTarget;)Lnet/minecraft/client/renderer/rendertype/RenderSetup$RenderSetupBuilder;
     737: invokevirtual #151                // Method net/minecraft/client/renderer/rendertype/RenderSetup$RenderSetupBuilder.affectsCrumbling:()Lnet/minecraft/client/renderer/rendertype/RenderSetup$RenderSetupBuilder;
     740: invokevirtual #261                // Method net/minecraft/client/renderer/rendertype/RenderSetup$RenderSetupBuilder.sortOnUpload:()Lnet/minecraft/client/renderer/rendertype/RenderSetup$RenderSetupBuilder;
     743: getstatic     #155                // Field net/minecraft/client/renderer/rendertype/RenderSetup$OutlineProperty.AFFECTS_OUTLINE:Lnet/minecraft/client/renderer/rendertype/RenderSetup$OutlineProperty;
     746: invokevirtual #159                // Method net/minecraft/client/renderer/rendertype/RenderSetup$RenderSetupBuilder.setOutline:(Lnet/minecraft/client/renderer/rendertype/RenderSetup$OutlineProperty;)Lnet/minecraft/client/renderer/rendertype/RenderSetup$RenderSetupBuilder;
     749: invokevirtual #163                // Method net/minecraft/client/renderer/rendertype/RenderSetup$RenderSetupBuilder.createRenderSetup:()Lnet/minecraft/client/renderer/rendertype/RenderSetup;
     752: invokestatic  #169                // Method net/minecraft/client/renderer/rendertype/RenderType.create:(Ljava/lang/String;Lnet/minecraft/client/renderer/rendertype/RenderSetup;)Lnet/minecraft/client/renderer/rendertype/RenderType;
     755: putstatic     #328                // Field TRIPWIRE_MOVING_BLOCk:Lnet/minecraft/client/renderer/rendertype/RenderType;
     758: ldc_w         #806                // String end_portal
     761: getstatic     #808                // Field net/minecraft/client/renderer/RenderPipelines.END_PORTAL:Lcom/mojang/blaze3d/pipeline/RenderPipeline;
     764: invokestatic  #125                // Method net/minecraft/client/renderer/rendertype/RenderSetup.builder:(Lcom/mojang/blaze3d/pipeline/RenderPipeline;)Lnet/minecraft/client/renderer/rendertype/RenderSetup$RenderSetupBuilder;
     767: ldc           #127                // String Sampler0
     769: getstatic     #813                // Field net/minecraft/client/renderer/blockentity/AbstractEndPortalRenderer.END_SKY_LOCATION:Lnet/minecraft/resources/Identifier;
     772: invokevirtual #131                // Method net/minecraft/client/renderer/rendertype/RenderSetup$RenderSetupBuilder.withTexture:(Ljava/lang/String;Lnet/minecraft/resources/Identifier;)Lnet/minecraft/client/renderer/rendertype/RenderSetup$RenderSetupBuilder;
     775: ldc_w         #815                // String Sampler1
     778: getstatic     #818                // Field net/minecraft/client/renderer/blockentity/AbstractEndPortalRenderer.END_PORTAL_LOCATION:Lnet/minecraft/resources/Identifier;
     781: invokevirtual #131                // Method net/minecraft/client/renderer/rendertype/RenderSetup$RenderSetupBuilder.withTexture:(Ljava/lang/String;Lnet/minecraft/resources/Identifier;)Lnet/minecraft/client/renderer/rendertype/RenderSetup$RenderSetupBuilder;
     784: invokevirtual #163                // Method net/minecraft/client/renderer/rendertype/RenderSetup$RenderSetupBuilder.createRenderSetup:()Lnet/minecraft/client/renderer/rendertype/RenderSetup;
     787: invokestatic  #169                // Method net/minecraft/client/renderer/rendertype/RenderType.create:(Ljava/lang/String;Lnet/minecraft/client/renderer/rendertype/RenderSetup;)Lnet/minecraft/client/renderer/rendertype/RenderType;
     790: putstatic     #331                // Field END_PORTAL:Lnet/minecraft/client/renderer/rendertype/RenderType;
     793: ldc_w         #820                // String end_gateway
     796: getstatic     #822                // Field net/minecraft/client/renderer/RenderPipelines.END_GATEWAY:Lcom/mojang/blaze3d/pipeline/RenderPipeline;
     799: invokestatic  #125                // Method net/minecraft/client/renderer/rendertype/RenderSetup.builder:(Lcom/mojang/blaze3d/pipeline/RenderPipeline;)Lnet/minecraft/client/renderer/rendertype/RenderSetup$RenderSetupBuilder;
     802: ldc           #127                // String Sampler0
     804: getstatic     #813                // Field net/minecraft/client/renderer/blockentity/AbstractEndPortalRenderer.END_SKY_LOCATION:Lnet/minecraft/resources/Identifier;
     807: invokevirtual #131                // Method net/minecraft/client/renderer/rendertype/RenderSetup$RenderSetupBuilder.withTexture:(Ljava/lang/String;Lnet/minecraft/resources/Identifier;)Lnet/minecraft/client/renderer/rendertype/RenderSetup$RenderSetupBuilder;
     810: ldc_w         #815                // String Sampler1
     813: getstatic     #818                // Field net/minecraft/client/renderer/blockentity/AbstractEndPortalRenderer.END_PORTAL_LOCATION:Lnet/minecraft/resources/Identifier;
     816: invokevirtual #131                // Method net/minecraft/client/renderer/rendertype/RenderSetup$RenderSetupBuilder.withTexture:(Ljava/lang/String;Lnet/minecraft/resources/Identifier;)Lnet/minecraft/client/renderer/rendertype/RenderSetup$RenderSetupBuilder;
     819: invokevirtual #163                // Method net/minecraft/client/renderer/rendertype/RenderSetup$RenderSetupBuilder.createRenderSetup:()Lnet/minecraft/client/renderer/rendertype/RenderSetup;
     822: invokestatic  #169                // Method net/minecraft/client/renderer/rendertype/RenderType.create:(Ljava/lang/String;Lnet/minecraft/client/renderer/rendertype/RenderSetup;)Lnet/minecraft/client/renderer/rendertype/RenderType;
     825: putstatic     #334                // Field END_GATEWAY:Lnet/minecraft/client/renderer/rendertype/RenderType;
     828: ldc_w         #823                // String lines
     831: getstatic     #825                // Field net/minecraft/client/renderer/RenderPipelines.LINES:Lcom/mojang/blaze3d/pipeline/RenderPipeline;
     834: invokestatic  #125                // Method net/minecraft/client/renderer/rendertype/RenderSetup.builder:(Lcom/mojang/blaze3d/pipeline/RenderPipeline;)Lnet/minecraft/client/renderer/rendertype/RenderSetup$RenderSetupBuilder;
     837: getstatic     #144                // Field net/minecraft/client/renderer/rendertype/LayeringTransform.VIEW_OFFSET_Z_LAYERING:Lnet/minecraft/client/renderer/rendertype/LayeringTransform;
     840: invokevirtual #148                // Method net/minecraft/client/renderer/rendertype/RenderSetup$RenderSetupBuilder.setLayeringTransform:(Lnet/minecraft/client/renderer/rendertype/LayeringTransform;)Lnet/minecraft/client/renderer/rendertype/RenderSetup$RenderSetupBuilder;
     843: getstatic     #515                // Field net/minecraft/client/renderer/rendertype/OutputTarget.ITEM_ENTITY_TARGET:Lnet/minecraft/client/renderer/rendertype/OutputTarget;
     846: invokevirtual #413                // Method net/minecraft/client/renderer/rendertype/RenderSetup$RenderSetupBuilder.setOutputTarget:(Lnet/minecraft/client/renderer/rendertype/OutputTarget;)Lnet/minecraft/client/renderer/rendertype/RenderSetup$RenderSetupBuilder;
     849: invokevirtual #163                // Method net/minecraft/client/renderer/rendertype/RenderSetup$RenderSetupBuilder.createRenderSetup:()Lnet/minecraft/client/renderer/rendertype/RenderSetup;
     852: invokestatic  #169                // Method net/minecraft/client/renderer/rendertype/RenderType.create:(Ljava/lang/String;Lnet/minecraft/client/renderer/rendertype/RenderSetup;)Lnet/minecraft/client/renderer/rendertype/RenderType;
     855: putstatic     #337                // Field LINES:Lnet/minecraft/client/renderer/rendertype/RenderType;
     858: ldc_w         #827                // String lines_translucent
     861: getstatic     #829                // Field net/minecraft/client/renderer/RenderPipelines.LINES_TRANSLUCENT:Lcom/mojang/blaze3d/pipeline/RenderPipeline;
     864: invokestatic  #125                // Method net/minecraft/client/renderer/rendertype/RenderSetup.builder:(Lcom/mojang/blaze3d/pipeline/RenderPipeline;)Lnet/minecraft/client/renderer/rendertype/RenderSetup$RenderSetupBuilder;
     867: getstatic     #144                // Field net/minecraft/client/renderer/rendertype/LayeringTransform.VIEW_OFFSET_Z_LAYERING:Lnet/minecraft/client/renderer/rendertype/LayeringTransform;
     870: invokevirtual #148                // Method net/minecraft/client/renderer/rendertype/RenderSetup$RenderSetupBuilder.setLayeringTransform:(Lnet/minecraft/client/renderer/rendertype/LayeringTransform;)Lnet/minecraft/client/renderer/rendertype/RenderSetup$RenderSetupBuilder;
     873: getstatic     #515                // Field net/minecraft/client/renderer/rendertype/OutputTarget.ITEM_ENTITY_TARGET:Lnet/minecraft/client/renderer/rendertype/OutputTarget;
     876: invokevirtual #413                // Method net/minecraft/client/renderer/rendertype/RenderSetup$RenderSetupBuilder.setOutputTarget:(Lnet/minecraft/client/renderer/rendertype/OutputTarget;)Lnet/minecraft/client/renderer/rendertype/RenderSetup$RenderSetupBuilder;
     879: invokevirtual #163                // Method net/minecraft/client/renderer/rendertype/RenderSetup$RenderSetupBuilder.createRenderSetup:()Lnet/minecraft/client/renderer/rendertype/RenderSetup;
     882: invokestatic  #169                // Method net/minecraft/client/renderer/rendertype/RenderType.create:(Ljava/lang/String;Lnet/minecraft/client/renderer/rendertype/RenderSetup;)Lnet/minecraft/client/renderer/rendertype/RenderType;
     885: putstatic     #340                // Field LINES_TRANSLUCENT:Lnet/minecraft/client/renderer/rendertype/RenderType;
     888: ldc_w         #831                // String secondary_block_outline
     891: getstatic     #833                // Field net/minecraft/client/renderer/RenderPipelines.SECONDARY_BLOCK_OUTLINE:Lcom/mojang/blaze3d/pipeline/RenderPipeline;
     894: invokestatic  #125                // Method net/minecraft/client/renderer/rendertype/RenderSetup.builder:(Lcom/mojang/blaze3d/pipeline/RenderPipeline;)Lnet/minecraft/client/renderer/rendertype/RenderSetup$RenderSetupBuilder;
     897: getstatic     #144                // Field net/minecraft/client/renderer/rendertype/LayeringTransform.VIEW_OFFSET_Z_LAYERING:Lnet/minecraft/client/renderer/rendertype/LayeringTransform;
     900: invokevirtual #148                // Method net/minecraft/client/renderer/rendertype/RenderSetup$RenderSetupBuilder.setLayeringTransform:(Lnet/minecraft/client/renderer/rendertype/LayeringTransform;)Lnet/minecraft/client/renderer/rendertype/RenderSetup$RenderSetupBuilder;
     903: getstatic     #515                // Field net/minecraft/client/renderer/rendertype/OutputTarget.ITEM_ENTITY_TARGET:Lnet/minecraft/client/renderer/rendertype/OutputTarget;
     906: invokevirtual #413                // Method net/minecraft/client/renderer/rendertype/RenderSetup$RenderSetupBuilder.setOutputTarget:(Lnet/minecraft/client/renderer/rendertype/OutputTarget;)Lnet/minecraft/client/renderer/rendertype/RenderSetup$RenderSetupBuilder;
     909: invokevirtual #163                // Method net/minecraft/client/renderer/rendertype/RenderSetup$RenderSetupBuilder.createRenderSetup:()Lnet/minecraft/client/renderer/rendertype/RenderSetup;
     912: invokestatic  #169                // Method net/minecraft/client/renderer/rendertype/RenderType.create:(Ljava/lang/String;Lnet/minecraft/client/renderer/rendertype/RenderSetup;)Lnet/minecraft/client/renderer/rendertype/RenderType;
     915: putstatic     #343                // Field SECONDARY_BLOCK_OUTLINE:Lnet/minecraft/client/renderer/rendertype/RenderType;
     918: ldc_w         #835                // String debug_filled_box
     921: getstatic     #837                // Field net/minecraft/client/renderer/RenderPipelines.DEBUG_FILLED_BOX:Lcom/mojang/blaze3d/pipeline/RenderPipeline;
     924: invokestatic  #125                // Method net/minecraft/client/renderer/rendertype/RenderSetup.builder:(Lcom/mojang/blaze3d/pipeline/RenderPipeline;)Lnet/minecraft/client/renderer/rendertype/RenderSetup$RenderSetupBuilder;
     927: invokevirtual #261                // Method net/minecraft/client/renderer/rendertype/RenderSetup$RenderSetupBuilder.sortOnUpload:()Lnet/minecraft/client/renderer/rendertype/RenderSetup$RenderSetupBuilder;
     930: getstatic     #144                // Field net/minecraft/client/renderer/rendertype/LayeringTransform.VIEW_OFFSET_Z_LAYERING:Lnet/minecraft/client/renderer/rendertype/LayeringTransform;
     933: invokevirtual #148                // Method net/minecraft/client/renderer/rendertype/RenderSetup$RenderSetupBuilder.setLayeringTransform:(Lnet/minecraft/client/renderer/rendertype/LayeringTransform;)Lnet/minecraft/client/renderer/rendertype/RenderSetup$RenderSetupBuilder;
     936: invokevirtual #163                // Method net/minecraft/client/renderer/rendertype/RenderSetup$RenderSetupBuilder.createRenderSetup:()Lnet/minecraft/client/renderer/rendertype/RenderSetup;
     939: invokestatic  #169                // Method net/minecraft/client/renderer/rendertype/RenderType.create:(Ljava/lang/String;Lnet/minecraft/client/renderer/rendertype/RenderSetup;)Lnet/minecraft/client/renderer/rendertype/RenderType;
     942: putstatic     #346                // Field DEBUG_FILLED_BOX:Lnet/minecraft/client/renderer/rendertype/RenderType;
     945: ldc_w         #839                // String debug_point
     948: getstatic     #842                // Field net/minecraft/client/renderer/RenderPipelines.DEBUG_POINTS:Lcom/mojang/blaze3d/pipeline/RenderPipeline;
     951: invokestatic  #125                // Method net/minecraft/client/renderer/rendertype/RenderSetup.builder:(Lcom/mojang/blaze3d/pipeline/RenderPipeline;)Lnet/minecraft/client/renderer/rendertype/RenderSetup$RenderSetupBuilder;
     954: invokevirtual #163                // Method net/minecraft/client/renderer/rendertype/RenderSetup$RenderSetupBuilder.createRenderSetup:()Lnet/minecraft/client/renderer/rendertype/RenderSetup;
     957: invokestatic  #169                // Method net/minecraft/client/renderer/rendertype/RenderType.create:(Ljava/lang/String;Lnet/minecraft/client/renderer/rendertype/RenderSetup;)Lnet/minecraft/client/renderer/rendertype/RenderType;
     960: putstatic     #349                // Field DEBUG_POINT:Lnet/minecraft/client/renderer/rendertype/RenderType;
     963: ldc_w         #844                // String debug_quads
     966: getstatic     #846                // Field net/minecraft/client/renderer/RenderPipelines.DEBUG_QUADS:Lcom/mojang/blaze3d/pipeline/RenderPipeline;
     969: invokestatic  #125                // Method net/minecraft/client/renderer/rendertype/RenderSetup.builder:(Lcom/mojang/blaze3d/pipeline/RenderPipeline;)Lnet/minecraft/client/renderer/rendertype/RenderSetup$RenderSetupBuilder;
     972: invokevirtual #261                // Method net/minecraft/client/renderer/rendertype/RenderSetup$RenderSetupBuilder.sortOnUpload:()Lnet/minecraft/client/renderer/rendertype/RenderSetup$RenderSetupBuilder;
     975: invokevirtual #163                // Method net/minecraft/client/renderer/rendertype/RenderSetup$RenderSetupBuilder.createRenderSetup:()Lnet/minecraft/client/renderer/rendertype/RenderSetup;
     978: invokestatic  #169                // Method net/minecraft/client/renderer/rendertype/RenderType.create:(Ljava/lang/String;Lnet/minecraft/client/renderer/rendertype/RenderSetup;)Lnet/minecraft/client/renderer/rendertype/RenderType;
     981: putstatic     #352                // Field DEBUG_QUADS:Lnet/minecraft/client/renderer/rendertype/RenderType;
     984: ldc_w         #848                // String debug_triangle_fan
     987: getstatic     #850                // Field net/minecraft/client/renderer/RenderPipelines.DEBUG_TRIANGLE_FAN:Lcom/mojang/blaze3d/pipeline/RenderPipeline;
     990: invokestatic  #125                // Method net/minecraft/client/renderer/rendertype/RenderSetup.builder:(Lcom/mojang/blaze3d/pipeline/RenderPipeline;)Lnet/minecraft/client/renderer/rendertype/RenderSetup$RenderSetupBuilder;
     993: invokevirtual #261                // Method net/minecraft/client/renderer/rendertype/RenderSetup$RenderSetupBuilder.sortOnUpload:()Lnet/minecraft/client/renderer/rendertype/RenderSetup$RenderSetupBuilder;
     996: invokevirtual #163                // Method net/minecraft/client/renderer/rendertype/RenderSetup$RenderSetupBuilder.createRenderSetup:()Lnet/minecraft/client/renderer/rendertype/RenderSetup;
     999: invokestatic  #169                // Method net/minecraft/client/renderer/rendertype/RenderType.create:(Ljava/lang/String;Lnet/minecraft/client/renderer/rendertype/RenderSetup;)Lnet/minecraft/client/renderer/rendertype/RenderType;
    1002: putstatic     #355                // Field DEBUG_TRIANGLE_FAN:Lnet/minecraft/client/renderer/rendertype/RenderType;
    1005: getstatic     #852                // Field net/minecraft/client/renderer/RenderPipelines.WEATHER_DEPTH_WRITE:Lcom/mojang/blaze3d/pipeline/RenderPipeline;
    1008: invokestatic  #854                // Method createWeather:(Lcom/mojang/blaze3d/pipeline/RenderPipeline;)Ljava/util/function/Function;
    1011: putstatic     #384                // Field WEATHER_DEPTH_WRITE:Ljava/util/function/Function;
    1014: getstatic     #856                // Field net/minecraft/client/renderer/RenderPipelines.WEATHER_NO_DEPTH_WRITE:Lcom/mojang/blaze3d/pipeline/RenderPipeline;
    1017: invokestatic  #854                // Method createWeather:(Lcom/mojang/blaze3d/pipeline/RenderPipeline;)Ljava/util/function/Function;
    1020: putstatic     #386                // Field WEATHER_NO_DEPTH_WRITE:Ljava/util/function/Function;
    1023: invokedynamic #860,  0            // InvokeDynamic #27:apply:()Ljava/util/function/Function;
    1028: invokestatic  #381                // Method net/minecraft/util/Util.memoize:(Ljava/util/function/Function;)Ljava/util/function/Function;
    1031: putstatic     #389                // Field BLOCK_SCREEN_EFFECT:Ljava/util/function/Function;
    1034: invokedynamic #864,  0            // InvokeDynamic #28:apply:()Ljava/util/function/Function;
    1039: invokestatic  #381                // Method net/minecraft/util/Util.memoize:(Ljava/util/function/Function;)Ljava/util/function/Function;
    1042: putstatic     #392                // Field FIRE_SCREEN_EFFECT:Ljava/util/function/Function;
    1045: return
}
